{
  "operation": {
    "id": "axs09",
    "label": "AXS 09",
    "full_name": "AXS ENERGIA 09 - Emissao 1 / Serie UNICA",
    "badge": "DEB",
    "category": "Debenture",
    "indexer": "IPCA + 10,98%",
    "description": "Debenture AXS 09 com capitalizacoes iniciais e pagamentos semestrais.",
    "issuer": "AXS ENERGIA UNIDADE 09 S.A.",
    "script_path": "/home/runner/work/Dashdivida_v2/Dashdivida_v2/Code final prontos/axs09_v1.py",
    "identity_fields": [
      {
        "label": "Codigo IF",
        "value": "AXS911"
      },
      {
        "label": "Codigo ISIN",
        "value": "BRAXS9DBS005"
      },
      {
        "label": "Emissor",
        "value": "AXS ENERGIA UNIDADE 09 S.A."
      }
    ],
    "overview_fields": [
      {
        "label": "Remuneracao",
        "value": "IPCA + 10.98%"
      },
      {
        "label": "Volume emitido",
        "value": "93000000"
      },
      {
        "label": "Quantidade emitida",
        "value": "93000"
      },
      {
        "label": "PU de emissao",
        "value": "1000"
      },
      {
        "label": "Data de emissao",
        "value": "20/09/2024"
      },
      {
        "label": "Inicio da rentabilidade",
        "value": "04/10/2024"
      },
      {
        "label": "Data de vencimento",
        "value": "15/09/2038"
      },
      {
        "label": "Pagamento de juros",
        "value": "Semestral"
      },
      {
        "label": "Amortizacao",
        "value": "Semestral"
      },
      {
        "label": "Distribuicao",
        "value": "Res CVM 160"
      },
      {
        "label": "Tipo de risco",
        "value": "-"
      },
      {
        "label": "Garantias",
        "value": "Alienacao Fiduciaria de Acoes, Alienacao Fiduciaria de Maquinas, Alienacao Fiduciaria de Direitos Creditorios"
      },
      {
        "label": "Saldo atual",
        "value": "109213702.7"
      },
      {
        "label": "Proximo PMT",
        "value": "9348800.88"
      }
    ],
    "pu_fields": [
      {
        "label": "PU cheio",
        "value": "1242.83627252"
      },
      {
        "label": "PU vazio",
        "value": "1180.24209972"
      },
      {
        "label": "PU juros",
        "value": "62.5941728"
      },
      {
        "label": "PU amortizacao",
        "value": "5.90121049"
      },
      {
        "label": "Principal atualizado",
        "value": "109762515.28"
      },
      {
        "label": "PMT da linha atual",
        "value": "6370070.65"
      }
    ]
  },
  "series": [
    {
      "date": "15/03/2025",
      "label": "Incorporacao Juros 1",
      "component": "",
      "component_label": "-",
      "payment": 0.0,
      "interest": 0.0,
      "amortization": 0.0,
      "balance": 100365104.82,
      "principal": 100365104.82,
      "pu_cheio": 1079.1946754500002,
      "pu_vazio": 1031.21711954,
      "pu_juros": 47.97755591,
      "pu_amort": 0.0,
      "pu_total": 0.0,
      "parsed_date": "15/03/2025",
      "sort_key": "Fluxo",
      "raw": {
        "Evento": "Incorporacao Juros 1",
        "Data_Ref": "15/03/2025",
        "Data_Pgto": "",
        "DU_Juros": 110,
        "Qtde_IPCA_Aplicados": 6,
        "Ultimo_Mes_NIk": "2025-02",
        "Ultimo_Mes_NIk_1": "2025-01",
        "Ultimo_Fator_C_IPCA": 1.01310065,
        "Fator_Juros": 1.046525174,
        "TAI_Amort": 0.0,
        "PU_VNa_Ini": 1000.0,
        "PU_VNa_Atualizado": 1031.21711954,
        "PU_Juros": 47.97755591,
        "PU_Juros_Incorporado": 47.97755591,
        "PU_Amort": 0.0,
        "PU_Total_Pago": 0.0,
        "PU_VNa_Fim": 1079.19467545,
        "Juros_R$": 0.0,
        "Amort_R$": 0.0,
        "PMT_Total": 0.0,
        "Saldo_Devedor_R$": 100365104.82
      },
      "total_interest_running": 0.0,
      "total_amortization_running": 0.0
    },
    {
      "date": "15/09/2025",
      "label": "Incorporacao Juros 2",
      "component": "",
      "component_label": "-",
      "payment": 0.0,
      "interest": 0.0,
      "amortization": 0.0,
      "balance": 107476199.25,
      "principal": 107476199.25,
      "pu_cheio": 1155.6580565000002,
      "pu_vazio": 1097.00091827,
      "pu_juros": 58.65713823,
      "pu_amort": 0.0,
      "pu_total": 0.0,
      "parsed_date": "15/09/2025",
      "sort_key": "Fluxo",
      "raw": {
        "Evento": "Incorporacao Juros 2",
        "Data_Ref": "15/09/2025",
        "Data_Pgto": "",
        "DU_Juros": 126,
        "Qtde_IPCA_Aplicados": 6,
        "Ultimo_Mes_NIk": "2025-08",
        "Ultimo_Mes_NIk_1": "2025-07",
        "Ultimo_Fator_C_IPCA": 0.99889934,
        "Fator_Juros": 1.053470455,
        "TAI_Amort": 0.0,
        "PU_VNa_Ini": 1079.19467545,
        "PU_VNa_Atualizado": 1097.00091827,
        "PU_Juros": 58.65713823,
        "PU_Juros_Incorporado": 58.65713823,
        "PU_Amort": 0.0,
        "PU_Total_Pago": 0.0,
        "PU_VNa_Fim": 1155.6580565,
        "Juros_R$": 0.0,
        "Amort_R$": 0.0,
        "PMT_Total": 0.0,
        "Saldo_Devedor_R$": 107476199.25
      },
      "total_interest_running": 0.0,
      "total_amortization_running": 0.0
    },
    {
      "date": "15/03/2026",
      "label": "Pagamento",
      "component": "",
      "component_label": "-",
      "payment": 6370070.65,
      "interest": 5821258.07,
      "amortization": 548812.58,
      "balance": 109213702.7,
      "principal": 109762515.28,
      "pu_cheio": 1242.83627252,
      "pu_vazio": 1180.24209972,
      "pu_juros": 62.5941728,
      "pu_amort": 5.90121049,
      "pu_total": 68.49538329,
      "parsed_date": "15/03/2026",
      "sort_key": "Fluxo",
      "raw": {
        "Evento": "Pagamento",
        "Data_Ref": "15/03/2026",
        "Data_Pgto": "15/03/2026",
        "DU_Juros": 125,
        "Qtde_IPCA_Aplicados": 6,
        "Ultimo_Mes_NIk": "2026-02",
        "Ultimo_Mes_NIk_1": "2026-01",
        "Ultimo_Fator_C_IPCA": 1.00699945,
        "Fator_Juros": 1.053035028,
        "TAI_Amort": 0.005,
        "PU_VNa_Ini": 1155.6580565,
        "PU_VNa_Atualizado": 1180.24209972,
        "PU_Juros": 62.5941728,
        "PU_Juros_Incorporado": 0.0,
        "PU_Amort": 5.90121049,
        "PU_Total_Pago": 68.49538329,
        "PU_VNa_Fim": 1174.34088923,
        "Juros_R$": 5821258.07,
        "Amort_R$": 548812.58,
        "PMT_Total": 6370070.65,
        "Saldo_Devedor_R$": 109213702.7
      },
      "total_interest_running": 5821258.07,
      "total_amortization_running": 548812.58
    },
    {
      "date": "15/09/2026",
      "label": "Pagamento",
      "component": "",
      "component_label": "-",
      "payment": 9348800.88,
      "interest": 5977947.13,
      "amortization": 3370853.75,
      "balance": 108428215.97,
      "principal": 111799069.72,
      "pu_cheio": 1266.41953603,
      "pu_vazio": 1202.14053467,
      "pu_juros": 64.27900136,
      "pu_amort": 36.24573926,
      "pu_total": 100.52474062,
      "parsed_date": "15/09/2026",
      "sort_key": "Fluxo",
      "raw": {
        "Evento": "Pagamento",
        "Data_Ref": "15/09/2026",
        "Data_Pgto": "15/09/2026",
        "DU_Juros": 126,
        "Qtde_IPCA_Aplicados": 6,
        "Ultimo_Mes_NIk": "2026-08",
        "Ultimo_Mes_NIk_1": "2026-07",
        "Ultimo_Fator_C_IPCA": 0.99815,
        "Fator_Juros": 1.053470455,
        "TAI_Amort": 0.030151,
        "PU_VNa_Ini": 1174.34088923,
        "PU_VNa_Atualizado": 1202.14053467,
        "PU_Juros": 64.27900136,
        "PU_Juros_Incorporado": 0.0,
        "PU_Amort": 36.24573926,
        "PU_Total_Pago": 100.52474062,
        "PU_VNa_Fim": 1165.89479541,
        "Juros_R$": 5977947.13,
        "Amort_R$": 3370853.75,
        "PMT_Total": 9348800.88,
        "Saldo_Devedor_R$": 108428215.97
      },
      "total_interest_running": 11799205.2,
      "total_amortization_running": 3919666.33
    },
    {
      "date": "15/03/2027",
      "label": "Pagamento",
      "component": "",
      "component_label": "-",
      "payment": 8816844.29,
      "interest": 5759427.5,
      "amortization": 3057416.79,
      "balance": 108279271.21,
      "principal": 111336688.0,
      "pu_cheio": 1259.09801607,
      "pu_vazio": 1197.16868814,
      "pu_juros": 61.92932793,
      "pu_amort": 32.87544934,
      "pu_total": 94.80477727,
      "parsed_date": "15/03/2027",
      "sort_key": "Fluxo",
      "raw": {
        "Evento": "Pagamento",
        "Data_Ref": "15/03/2027",
        "Data_Pgto": "15/03/2027",
        "DU_Juros": 122,
        "Qtde_IPCA_Aplicados": 6,
        "Ultimo_Mes_NIk": "2027-02",
        "Ultimo_Mes_NIk_1": "2027-01",
        "Ultimo_Fator_C_IPCA": 1.006192,
        "Fator_Juros": 1.051729826,
        "TAI_Amort": 0.027461,
        "PU_VNa_Ini": 1165.89479541,
        "PU_VNa_Atualizado": 1197.16868814,
        "PU_Juros": 61.92932793,
        "PU_Juros_Incorporado": 0.0,
        "PU_Amort": 32.87544934,
        "PU_Total_Pago": 94.80477727,
        "PU_VNa_Fim": 1164.2932388,
        "Juros_R$": 5759427.5,
        "Amort_R$": 3057416.79,
        "PMT_Total": 8816844.29,
        "Saldo_Devedor_R$": 108279271.21
      },
      "total_interest_running": 17558632.7,
      "total_amortization_running": 6977083.12
    },
    {
      "date": "15/09/2027",
      "label": "Pagamento",
      "component": "",
      "component_label": "-",
      "payment": 9213561.04,
      "interest": 5985878.84,
      "amortization": 3227682.2,
      "balance": 106924600.86,
      "principal": 110152283.06,
      "pu_cheio": 1248.79743982,
      "pu_vazio": 1184.43315119,
      "pu_juros": 64.36428863,
      "pu_amort": 34.70626019,
      "pu_total": 99.07054882,
      "parsed_date": "15/09/2027",
      "sort_key": "Fluxo",
      "raw": {
        "Evento": "Pagamento",
        "Data_Ref": "15/09/2027",
        "Data_Pgto": "15/09/2027",
        "DU_Juros": 128,
        "Qtde_IPCA_Aplicados": 6,
        "Ultimo_Mes_NIk": "2027-08",
        "Ultimo_Mes_NIk_1": "2027-07",
        "Ultimo_Fator_C_IPCA": 1.0018,
        "Fator_Juros": 1.05434185,
        "TAI_Amort": 0.029302,
        "PU_VNa_Ini": 1164.2932388,
        "PU_VNa_Atualizado": 1184.43315119,
        "PU_Juros": 64.36428863,
        "PU_Juros_Incorporado": 0.0,
        "PU_Amort": 34.70626019,
        "PU_Total_Pago": 99.07054882,
        "PU_VNa_Fim": 1149.726891,
        "Juros_R$": 5985878.84,
        "Amort_R$": 3227682.2,
        "PMT_Total": 9213561.04,
        "Saldo_Devedor_R$": 106924600.86
      },
      "total_interest_running": 23544511.54,
      "total_amortization_running": 10204765.32
    },
    {
      "date": "15/03/2028",
      "label": "Pagamento",
      "component": "",
      "component_label": "-",
      "payment": 9104738.26,
      "interest": 5802190.36,
      "amortization": 3302547.9,
      "balance": 106100436.85,
      "principal": 109402984.75,
      "pu_cheio": 1238.7653238,
      "pu_vazio": 1176.37618015,
      "pu_juros": 62.38914365,
      "pu_amort": 35.51126775,
      "pu_total": 97.9004114,
      "parsed_date": "15/03/2028",
      "sort_key": "Fluxo",
      "raw": {
        "Evento": "Pagamento",
        "Data_Ref": "15/03/2028",
        "Data_Pgto": "15/03/2028",
        "DU_Juros": 125,
        "Qtde_IPCA_Aplicados": 6,
        "Ultimo_Mes_NIk": "2028-02",
        "Ultimo_Mes_NIk_1": "2028-01",
        "Ultimo_Fator_C_IPCA": 1.00545,
        "Fator_Juros": 1.053035028,
        "TAI_Amort": 0.030187,
        "PU_VNa_Ini": 1149.726891,
        "PU_VNa_Atualizado": 1176.37618015,
        "PU_Juros": 62.38914365,
        "PU_Juros_Incorporado": 0.0,
        "PU_Amort": 35.51126775,
        "PU_Total_Pago": 97.9004114,
        "PU_VNa_Fim": 1140.8649124,
        "Juros_R$": 5802190.36,
        "Amort_R$": 3302547.9,
        "PMT_Total": 9104738.26,
        "Saldo_Devedor_R$": 106100436.85
      },
      "total_interest_running": 29346701.9,
      "total_amortization_running": 13507313.22
    },
    {
      "date": "15/09/2028",
      "label": "Pagamento",
      "component": "",
      "component_label": "-",
      "payment": 9482184.82,
      "interest": 5817610.41,
      "amortization": 3664574.41,
      "balance": 104256688.82,
      "principal": 107921263.22999999,
      "pu_cheio": 1222.9986413899999,
      "pu_vazio": 1160.4436907,
      "pu_juros": 62.55495069,
      "pu_amort": 39.40402596,
      "pu_total": 101.95897665,
      "parsed_date": "15/09/2028",
      "sort_key": "Fluxo",
      "raw": {
        "Evento": "Pagamento",
        "Data_Ref": "15/09/2028",
        "Data_Pgto": "15/09/2028",
        "DU_Juros": 127,
        "Qtde_IPCA_Aplicados": 6,
        "Ultimo_Mes_NIk": "2028-08",
        "Ultimo_Mes_NIk_1": "2028-07",
        "Ultimo_Fator_C_IPCA": 1.00309268,
        "Fator_Juros": 1.053906063,
        "TAI_Amort": 0.033956,
        "PU_VNa_Ini": 1140.8649124,
        "PU_VNa_Atualizado": 1160.4436907,
        "PU_Juros": 62.55495069,
        "PU_Juros_Incorporado": 0.0,
        "PU_Amort": 39.40402596,
        "PU_Total_Pago": 101.95897665,
        "PU_VNa_Fim": 1121.03966474,
        "Juros_R$": 5817610.41,
        "Amort_R$": 3664574.41,
        "PMT_Total": 9482184.82,
        "Saldo_Devedor_R$": 104256688.82
      },
      "total_interest_running": 35164312.31,
      "total_amortization_running": 17171887.630000003
    },
    {
      "date": "15/03/2029",
      "label": "Pagamento",
      "component": "",
      "component_label": "-",
      "payment": 9176850.8,
      "interest": 5445456.04,
      "amortization": 3731394.76,
      "balance": 102427948.5,
      "principal": 106159343.26,
      "pu_cheio": 1200.05160536,
      "pu_vazio": 1141.49831462,
      "pu_juros": 58.55329074,
      "pu_amort": 40.12252426,
      "pu_total": 98.675815,
      "parsed_date": "15/03/2029",
      "sort_key": "Fluxo",
      "raw": {
        "Evento": "Pagamento",
        "Data_Ref": "15/03/2029",
        "Data_Pgto": "15/03/2029",
        "DU_Juros": 121,
        "Qtde_IPCA_Aplicados": 6,
        "Ultimo_Mes_NIk": "2029-02",
        "Ultimo_Mes_NIk_1": "2029-01",
        "Ultimo_Fator_C_IPCA": 1.00287089,
        "Fator_Juros": 1.051295118,
        "TAI_Amort": 0.035149,
        "PU_VNa_Ini": 1121.03966474,
        "PU_VNa_Atualizado": 1141.49831462,
        "PU_Juros": 58.55329074,
        "PU_Juros_Incorporado": 0.0,
        "PU_Amort": 40.12252426,
        "PU_Total_Pago": 98.675815,
        "PU_VNa_Fim": 1101.37579036,
        "Juros_R$": 5445456.04,
        "Amort_R$": 3731394.76,
        "PMT_Total": 9176850.8,
        "Saldo_Devedor_R$": 102427948.5
      },
      "total_interest_running": 40609768.35,
      "total_amortization_running": 20903282.39
    },
    {
      "date": "15/09/2029",
      "label": "Pagamento",
      "component": "",
      "component_label": "-",
      "payment": 10091614.99,
      "interest": 5662693.38,
      "amortization": 4428921.61,
      "balance": 99776094.89,
      "principal": 104205016.5,
      "pu_cheio": 1181.37322445,
      "pu_vazio": 1120.48404837,
      "pu_juros": 60.88917608,
      "pu_amort": 47.62281302,
      "pu_total": 108.5119891,
      "parsed_date": "15/09/2029",
      "sort_key": "Fluxo",
      "raw": {
        "Evento": "Pagamento",
        "Data_Ref": "15/09/2029",
        "Data_Pgto": "15/09/2029",
        "DU_Juros": 128,
        "Qtde_IPCA_Aplicados": 6,
        "Ultimo_Mes_NIk": "2029-08",
        "Ultimo_Mes_NIk_1": "2029-07",
        "Ultimo_Fator_C_IPCA": 1.00287089,
        "Fator_Juros": 1.05434185,
        "TAI_Amort": 0.042502,
        "PU_VNa_Ini": 1101.37579036,
        "PU_VNa_Atualizado": 1120.48404837,
        "PU_Juros": 60.88917608,
        "PU_Juros_Incorporado": 0.0,
        "PU_Amort": 47.62281302,
        "PU_Total_Pago": 108.5119891,
        "PU_VNa_Fim": 1072.86123535,
        "Juros_R$": 5662693.38,
        "Amort_R$": 4428921.61,
        "PMT_Total": 10091614.99,
        "Saldo_Devedor_R$": 99776094.89
      },
      "total_interest_running": 46272461.730000004,
      "total_amortization_running": 25332204.0
    },
    {
      "date": "15/03/2030",
      "label": "Pagamento",
      "component": "",
      "component_label": "-",
      "payment": 9326286.34,
      "interest": 5206821.48,
      "amortization": 4119464.86,
      "balance": 97387689.84,
      "principal": 101507154.7,
      "pu_cheio": 1147.4621093800001,
      "pu_vazio": 1091.47478167,
      "pu_juros": 55.98732771,
      "pu_amort": 44.29532106,
      "pu_total": 100.28264877,
      "parsed_date": "15/03/2030",
      "sort_key": "Fluxo",
      "raw": {
        "Evento": "Pagamento",
        "Data_Ref": "15/03/2030",
        "Data_Pgto": "15/03/2030",
        "DU_Juros": 121,
        "Qtde_IPCA_Aplicados": 6,
        "Ultimo_Mes_NIk": "2030-02",
        "Ultimo_Mes_NIk_1": "2030-01",
        "Ultimo_Fator_C_IPCA": 1.00287089,
        "Fator_Juros": 1.051295118,
        "TAI_Amort": 0.040583,
        "PU_VNa_Ini": 1072.86123535,
        "PU_VNa_Atualizado": 1091.47478167,
        "PU_Juros": 55.98732771,
        "PU_Juros_Incorporado": 0.0,
        "PU_Amort": 44.29532106,
        "PU_Total_Pago": 100.28264877,
        "PU_VNa_Fim": 1047.17946061,
        "Juros_R$": 5206821.48,
        "Amort_R$": 4119464.86,
        "PMT_Total": 9326286.34,
        "Saldo_Devedor_R$": 97387689.84
      },
      "total_interest_running": 51479283.21000001,
      "total_amortization_running": 29451668.86
    },
    {
      "date": "15/09/2030",
      "label": "Pagamento",
      "component": "",
      "component_label": "-",
      "payment": 9967955.35,
      "interest": 5384044.43,
      "amortization": 4583910.92,
      "balance": 94493401.22,
      "principal": 99077312.14,
      "pu_cheio": 1123.24039332,
      "pu_vazio": 1065.34744241,
      "pu_juros": 57.89295091,
      "pu_amort": 49.28936477,
      "pu_total": 107.18231568,
      "parsed_date": "15/09/2030",
      "sort_key": "Fluxo",
      "raw": {
        "Evento": "Pagamento",
        "Data_Ref": "15/09/2030",
        "Data_Pgto": "15/09/2030",
        "DU_Juros": 128,
        "Qtde_IPCA_Aplicados": 6,
        "Ultimo_Mes_NIk": "2030-08",
        "Ultimo_Mes_NIk_1": "2030-07",
        "Ultimo_Fator_C_IPCA": 1.00287089,
        "Fator_Juros": 1.05434185,
        "TAI_Amort": 0.046266,
        "PU_VNa_Ini": 1047.17946061,
        "PU_VNa_Atualizado": 1065.34744241,
        "PU_Juros": 57.89295091,
        "PU_Juros_Incorporado": 0.0,
        "PU_Amort": 49.28936477,
        "PU_Total_Pago": 107.18231568,
        "PU_VNa_Fim": 1016.05807764,
        "Juros_R$": 5384044.43,
        "Amort_R$": 4583910.92,
        "PMT_Total": 9967955.35,
        "Saldo_Devedor_R$": 94493401.22
      },
      "total_interest_running": 56863327.64000001,
      "total_amortization_running": 34035579.78
    },
    {
      "date": "15/03/2031",
      "label": "Pagamento",
      "component": "",
      "component_label": "-",
      "payment": 10419938.61,
      "interest": 5073006.29,
      "amortization": 5346932.32,
      "balance": 91098455.78,
      "principal": 96445388.1,
      "pu_cheio": 1091.5956385700001,
      "pu_vazio": 1037.04718382,
      "pu_juros": 54.54845475,
      "pu_amort": 57.49389587,
      "pu_total": 112.04235062,
      "parsed_date": "15/03/2031",
      "sort_key": "Fluxo",
      "raw": {
        "Evento": "Pagamento",
        "Data_Ref": "15/03/2031",
        "Data_Pgto": "15/03/2031",
        "DU_Juros": 124,
        "Qtde_IPCA_Aplicados": 6,
        "Ultimo_Mes_NIk": "2031-02",
        "Ultimo_Mes_NIk_1": "2031-01",
        "Ultimo_Fator_C_IPCA": 1.0045,
        "Fator_Juros": 1.052599781,
        "TAI_Amort": 0.05544,
        "PU_VNa_Ini": 1016.05807764,
        "PU_VNa_Atualizado": 1037.04718382,
        "PU_Juros": 54.54845475,
        "PU_Juros_Incorporado": 0.0,
        "PU_Amort": 57.49389587,
        "PU_Total_Pago": 112.04235062,
        "PU_VNa_Fim": 979.55328795,
        "Juros_R$": 5073006.29,
        "Amort_R$": 5346932.32,
        "PMT_Total": 10419938.61,
        "Saldo_Devedor_R$": 91098455.78
      },
      "total_interest_running": 61936333.93000001,
      "total_amortization_running": 39382512.1
    },
    {
      "date": "15/09/2031",
      "label": "Pagamento",
      "component": "",
      "component_label": "-",
      "payment": 10497017.29,
      "interest": 5004083.43,
      "amortization": 5492933.86,
      "balance": 88093017.97,
      "principal": 93585951.83,
      "pu_cheio": 1060.10790593,
      "pu_vazio": 1006.30055727,
      "pu_juros": 53.80734866,
      "pu_amort": 59.0638049,
      "pu_total": 112.87115356,
      "parsed_date": "15/09/2031",
      "sort_key": "Fluxo",
      "raw": {
        "Evento": "Pagamento",
        "Data_Ref": "15/09/2031",
        "Data_Pgto": "15/09/2031",
        "DU_Juros": 126,
        "Qtde_IPCA_Aplicados": 6,
        "Ultimo_Mes_NIk": "2031-08",
        "Ultimo_Mes_NIk_1": "2031-07",
        "Ultimo_Fator_C_IPCA": 1.0045,
        "Fator_Juros": 1.053470455,
        "TAI_Amort": 0.058694,
        "PU_VNa_Ini": 979.55328795,
        "PU_VNa_Atualizado": 1006.30055727,
        "PU_Juros": 53.80734866,
        "PU_Juros_Incorporado": 0.0,
        "PU_Amort": 59.0638049,
        "PU_Total_Pago": 112.87115356,
        "PU_VNa_Fim": 947.23675237,
        "Juros_R$": 5004083.43,
        "Amort_R$": 5492933.86,
        "PMT_Total": 10497017.29,
        "Saldo_Devedor_R$": 88093017.97
      },
      "total_interest_running": 66940417.36000001,
      "total_amortization_running": 44875445.96
    },
    {
      "date": "15/03/2032",
      "label": "Pagamento",
      "component": "",
      "component_label": "-",
      "payment": 10442528.05,
      "interest": 4799587.77,
      "amortization": 5642940.28,
      "balance": 84855508.52,
      "principal": 90498448.8,
      "pu_cheio": 1024.7100705799999,
      "pu_vazio": 973.10159998,
      "pu_juros": 51.6084706,
      "pu_amort": 60.67677716,
      "pu_total": 112.28524776,
      "parsed_date": "15/03/2032",
      "sort_key": "Fluxo",
      "raw": {
        "Evento": "Pagamento",
        "Data_Ref": "15/03/2032",
        "Data_Pgto": "15/03/2032",
        "DU_Juros": 125,
        "Qtde_IPCA_Aplicados": 6,
        "Ultimo_Mes_NIk": "2032-02",
        "Ultimo_Mes_NIk_1": "2032-01",
        "Ultimo_Fator_C_IPCA": 1.0045,
        "Fator_Juros": 1.053035028,
        "TAI_Amort": 0.062354,
        "PU_VNa_Ini": 947.23675237,
        "PU_VNa_Atualizado": 973.10159998,
        "PU_Juros": 51.6084706,
        "PU_Juros_Incorporado": 0.0,
        "PU_Amort": 60.67677716,
        "PU_Total_Pago": 112.28524776,
        "PU_VNa_Fim": 912.42482282,
        "Juros_R$": 4799587.77,
        "Amort_R$": 5642940.28,
        "PMT_Total": 10442528.05,
        "Saldo_Devedor_R$": 84855508.52
      },
      "total_interest_running": 71740005.13000001,
      "total_amortization_running": 50518386.24
    },
    {
      "date": "15/09/2032",
      "label": "Pagamento",
      "component": "",
      "component_label": "-",
      "payment": 10534090.67,
      "interest": 4737116.94,
      "amortization": 5796973.73,
      "balance": 81375563.55,
      "principal": 87172537.28,
      "pu_cheio": 988.2758519,
      "pu_vazio": 937.33911056,
      "pu_juros": 50.93674134,
      "pu_amort": 62.33305085,
      "pu_total": 113.26979219,
      "parsed_date": "15/09/2032",
      "sort_key": "Fluxo",
      "raw": {
        "Evento": "Pagamento",
        "Data_Ref": "15/09/2032",
        "Data_Pgto": "15/09/2032",
        "DU_Juros": 128,
        "Qtde_IPCA_Aplicados": 6,
        "Ultimo_Mes_NIk": "2032-08",
        "Ultimo_Mes_NIk_1": "2032-07",
        "Ultimo_Fator_C_IPCA": 1.0045,
        "Fator_Juros": 1.05434185,
        "TAI_Amort": 0.0665,
        "PU_VNa_Ini": 912.42482282,
        "PU_VNa_Atualizado": 937.33911056,
        "PU_Juros": 50.93674134,
        "PU_Juros_Incorporado": 0.0,
        "PU_Amort": 62.33305085,
        "PU_Total_Pago": 113.26979219,
        "PU_VNa_Fim": 875.00605971,
        "Juros_R$": 4737116.94,
        "Amort_R$": 5796973.73,
        "PMT_Total": 10534090.67,
        "Saldo_Devedor_R$": 81375563.55
      },
      "total_interest_running": 76477122.07000001,
      "total_amortization_running": 56315359.97
    },
    {
      "date": "15/03/2033",
      "label": "Pagamento",
      "component": "",
      "component_label": "-",
      "payment": 10352537.62,
      "interest": 4397213.9,
      "amortization": 5955323.72,
      "balance": 77642246.68,
      "principal": 83597570.4,
      "pu_cheio": 946.18047631,
      "pu_vazio": 898.89860647,
      "pu_juros": 47.28186984,
      "pu_amort": 64.03573892,
      "pu_total": 111.31760876,
      "parsed_date": "15/03/2033",
      "sort_key": "Fluxo",
      "raw": {
        "Evento": "Pagamento",
        "Data_Ref": "15/03/2033",
        "Data_Pgto": "15/03/2033",
        "DU_Juros": 124,
        "Qtde_IPCA_Aplicados": 6,
        "Ultimo_Mes_NIk": "2033-02",
        "Ultimo_Mes_NIk_1": "2033-01",
        "Ultimo_Fator_C_IPCA": 1.0045,
        "Fator_Juros": 1.052599781,
        "TAI_Amort": 0.071238,
        "PU_VNa_Ini": 875.00605971,
        "PU_VNa_Atualizado": 898.89860647,
        "PU_Juros": 47.28186984,
        "PU_Juros_Incorporado": 0.0,
        "PU_Amort": 64.03573892,
        "PU_Total_Pago": 111.31760876,
        "PU_VNa_Fim": 834.86286755,
        "Juros_R$": 4397213.9,
        "Amort_R$": 5955323.72,
        "PMT_Total": 10352537.62,
        "Saldo_Devedor_R$": 77642246.68
      },
      "total_interest_running": 80874335.97000001,
      "total_amortization_running": 62270683.69
    },
    {
      "date": "15/09/2033",
      "label": "Pagamento",
      "component": "",
      "component_label": "-",
      "payment": 9687599.54,
      "interest": 4334431.66,
      "amortization": 5353167.88,
      "balance": 74409145.27,
      "principal": 79762313.14999999,
      "pu_cheio": 904.2660732200001,
      "pu_vazio": 857.65928121,
      "pu_juros": 46.60679201,
      "pu_amort": 57.56094499,
      "pu_total": 104.167737,
      "parsed_date": "15/09/2033",
      "sort_key": "Fluxo",
      "raw": {
        "Evento": "Pagamento",
        "Data_Ref": "15/09/2033",
        "Data_Pgto": "15/09/2033",
        "DU_Juros": 128,
        "Qtde_IPCA_Aplicados": 6,
        "Ultimo_Mes_NIk": "2033-08",
        "Ultimo_Mes_NIk_1": "2033-07",
        "Ultimo_Fator_C_IPCA": 1.0045,
        "Fator_Juros": 1.05434185,
        "TAI_Amort": 0.067114,
        "PU_VNa_Ini": 834.86286755,
        "PU_VNa_Atualizado": 857.65928121,
        "PU_Juros": 46.60679201,
        "PU_Juros_Incorporado": 0.0,
        "PU_Amort": 57.56094499,
        "PU_Total_Pago": 104.167737,
        "PU_VNa_Fim": 800.09833622,
        "Juros_R$": 4334431.66,
        "Amort_R$": 5353167.88,
        "PMT_Total": 9687599.54,
        "Saldo_Devedor_R$": 74409145.27
      },
      "total_interest_running": 85208767.63000001,
      "total_amortization_running": 67623851.57
    },
    {
      "date": "15/03/2034",
      "label": "Pagamento",
      "component": "",
      "component_label": "-",
      "payment": 11091332.88,
      "interest": 4020776.18,
      "amortization": 7070556.7,
      "balance": 69370373.33,
      "principal": 76440930.03,
      "pu_cheio": 865.1796367100001,
      "pu_vazio": 821.94548425,
      "pu_juros": 43.23415246,
      "pu_amort": 76.02749145,
      "pu_total": 119.26164391,
      "parsed_date": "15/03/2034",
      "sort_key": "Fluxo",
      "raw": {
        "Evento": "Pagamento",
        "Data_Ref": "15/03/2034",
        "Data_Pgto": "15/03/2034",
        "DU_Juros": 124,
        "Qtde_IPCA_Aplicados": 6,
        "Ultimo_Mes_NIk": "2034-02",
        "Ultimo_Mes_NIk_1": "2034-01",
        "Ultimo_Fator_C_IPCA": 1.0045,
        "Fator_Juros": 1.052599781,
        "TAI_Amort": 0.092497,
        "PU_VNa_Ini": 800.09833622,
        "PU_VNa_Atualizado": 821.94548425,
        "PU_Juros": 43.23415246,
        "PU_Juros_Incorporado": 0.0,
        "PU_Amort": 76.02749145,
        "PU_Total_Pago": 119.26164391,
        "PU_VNa_Fim": 745.9179928,
        "Juros_R$": 4020776.18,
        "Amort_R$": 7070556.7,
        "PMT_Total": 11091332.88,
        "Saldo_Devedor_R$": 69370373.33
      },
      "total_interest_running": 89229543.81000002,
      "total_amortization_running": 74694408.27
    },
    {
      "date": "15/09/2034",
      "label": "Pagamento",
      "component": "",
      "component_label": "-",
      "payment": 9491091.39,
      "interest": 3841592.48,
      "amortization": 5649498.91,
      "balance": 65615072.61,
      "principal": 71264571.52,
      "pu_cheio": 807.5931612200001,
      "pu_vazio": 766.28571519,
      "pu_juros": 41.30744603,
      "pu_amort": 60.74730007,
      "pu_total": 102.0547461,
      "parsed_date": "15/09/2034",
      "sort_key": "Fluxo",
      "raw": {
        "Evento": "Pagamento",
        "Data_Ref": "15/09/2034",
        "Data_Pgto": "15/09/2034",
        "DU_Juros": 127,
        "Qtde_IPCA_Aplicados": 6,
        "Ultimo_Mes_NIk": "2034-08",
        "Ultimo_Mes_NIk_1": "2034-07",
        "Ultimo_Fator_C_IPCA": 1.0045,
        "Fator_Juros": 1.053906063,
        "TAI_Amort": 0.079275,
        "PU_VNa_Ini": 745.9179928,
        "PU_VNa_Atualizado": 766.28571519,
        "PU_Juros": 41.30744603,
        "PU_Juros_Incorporado": 0.0,
        "PU_Amort": 60.74730007,
        "PU_Total_Pago": 102.0547461,
        "PU_VNa_Fim": 705.53841512,
        "Juros_R$": 3841592.48,
        "Amort_R$": 5649498.91,
        "PMT_Total": 9491091.39,
        "Saldo_Devedor_R$": 65615072.61
      },
      "total_interest_running": 93071136.29000002,
      "total_amortization_running": 80343907.17999999
    },
    {
      "date": "15/03/2035",
      "label": "Pagamento",
      "component": "",
      "component_label": "-",
      "payment": 10090525.83,
      "interest": 3457636.18,
      "amortization": 6632889.65,
      "balance": 60773840.48,
      "principal": 67406730.13,
      "pu_cheio": 761.9824334,
      "pu_vazio": 724.80354979,
      "pu_juros": 37.17888361,
      "pu_amort": 71.3213941,
      "pu_total": 108.50027771,
      "parsed_date": "15/03/2035",
      "sort_key": "Fluxo",
      "raw": {
        "Evento": "Pagamento",
        "Data_Ref": "15/03/2035",
        "Data_Pgto": "15/03/2035",
        "DU_Juros": 121,
        "Qtde_IPCA_Aplicados": 6,
        "Ultimo_Mes_NIk": "2035-02",
        "Ultimo_Mes_NIk_1": "2035-01",
        "Ultimo_Fator_C_IPCA": 1.0045,
        "Fator_Juros": 1.051295118,
        "TAI_Amort": 0.098401,
        "PU_VNa_Ini": 705.53841512,
        "PU_VNa_Atualizado": 724.80354979,
        "PU_Juros": 37.17888361,
        "PU_Juros_Incorporado": 0.0,
        "PU_Amort": 71.3213941,
        "PU_Total_Pago": 108.50027771,
        "PU_VNa_Fim": 653.48215569,
        "Juros_R$": 3457636.18,
        "Amort_R$": 6632889.65,
        "PMT_Total": 10090525.83,
        "Saldo_Devedor_R$": 60773840.48
      },
      "total_interest_running": 96528772.47000003,
      "total_amortization_running": 86976796.83
    },
    {
      "date": "15/09/2035",
      "label": "Pagamento",
      "component": "",
      "component_label": "-",
      "payment": 11058489.84,
      "interest": 3392741.31,
      "amortization": 7665748.53,
      "balance": 54767556.83,
      "principal": 62433305.36,
      "pu_cheio": 707.8069534699999,
      "pu_vazio": 671.32586407,
      "pu_juros": 36.4810894,
      "pu_amort": 82.42740356,
      "pu_total": 118.90849296,
      "parsed_date": "15/09/2035",
      "sort_key": "Fluxo",
      "raw": {
        "Evento": "Pagamento",
        "Data_Ref": "15/09/2035",
        "Data_Pgto": "15/09/2035",
        "DU_Juros": 128,
        "Qtde_IPCA_Aplicados": 6,
        "Ultimo_Mes_NIk": "2035-08",
        "Ultimo_Mes_NIk_1": "2035-07",
        "Ultimo_Fator_C_IPCA": 1.0045,
        "Fator_Juros": 1.05434185,
        "TAI_Amort": 0.122783,
        "PU_VNa_Ini": 653.48215569,
        "PU_VNa_Atualizado": 671.32586407,
        "PU_Juros": 36.4810894,
        "PU_Juros_Incorporado": 0.0,
        "PU_Amort": 82.42740356,
        "PU_Total_Pago": 118.90849296,
        "PU_VNa_Fim": 588.89846051,
        "Juros_R$": 3392741.31,
        "Amort_R$": 7665748.53,
        "PMT_Total": 11058489.84,
        "Saldo_Devedor_R$": 54767556.83
      },
      "total_interest_running": 99921513.78000003,
      "total_amortization_running": 94642545.36
    },
    {
      "date": "15/03/2036",
      "label": "Pagamento",
      "component": "",
      "component_label": "-",
      "payment": 10785554.24,
      "interest": 2910476.06,
      "amortization": 7875078.18,
      "balance": 48387938.48,
      "principal": 56263016.66,
      "pu_cheio": 636.27411524,
      "pu_vazio": 604.97867372,
      "pu_juros": 31.29544152,
      "pu_amort": 84.67825998,
      "pu_total": 115.9737015,
      "parsed_date": "15/03/2036",
      "sort_key": "Fluxo",
      "raw": {
        "Evento": "Pagamento",
        "Data_Ref": "15/03/2036",
        "Data_Pgto": "15/03/2036",
        "DU_Juros": 122,
        "Qtde_IPCA_Aplicados": 6,
        "Ultimo_Mes_NIk": "2036-02",
        "Ultimo_Mes_NIk_1": "2036-01",
        "Ultimo_Fator_C_IPCA": 1.0045,
        "Fator_Juros": 1.051729826,
        "TAI_Amort": 0.139969,
        "PU_VNa_Ini": 588.89846051,
        "PU_VNa_Atualizado": 604.97867372,
        "PU_Juros": 31.29544152,
        "PU_Juros_Incorporado": 0.0,
        "PU_Amort": 84.67825998,
        "PU_Total_Pago": 115.9737015,
        "PU_VNa_Fim": 520.30041374,
        "Juros_R$": 2910476.06,
        "Amort_R$": 7875078.18,
        "PMT_Total": 10785554.24,
        "Saldo_Devedor_R$": 48387938.48
      },
      "total_interest_running": 102831989.84000003,
      "total_amortization_running": 102517623.53999999
    },
    {
      "date": "15/09/2036",
      "label": "Pagamento",
      "component": "",
      "component_label": "-",
      "payment": 11646987.39,
      "interest": 2657973.49,
      "amortization": 8989013.9,
      "balance": 40720185.24,
      "principal": 49709199.14,
      "pu_cheio": 563.0878777600001,
      "pu_vazio": 534.5075176,
      "pu_juros": 28.58036016,
      "pu_amort": 96.65606342,
      "pu_total": 125.23642358,
      "parsed_date": "15/09/2036",
      "sort_key": "Fluxo",
      "raw": {
        "Evento": "Pagamento",
        "Data_Ref": "15/09/2036",
        "Data_Pgto": "15/09/2036",
        "DU_Juros": 126,
        "Qtde_IPCA_Aplicados": 6,
        "Ultimo_Mes_NIk": "2036-08",
        "Ultimo_Mes_NIk_1": "2036-07",
        "Ultimo_Fator_C_IPCA": 1.0045,
        "Fator_Juros": 1.053470455,
        "TAI_Amort": 0.180832,
        "PU_VNa_Ini": 520.30041374,
        "PU_VNa_Atualizado": 534.5075176,
        "PU_Juros": 28.58036016,
        "PU_Juros_Incorporado": 0.0,
        "PU_Amort": 96.65606342,
        "PU_Total_Pago": 125.23642358,
        "PU_VNa_Fim": 437.85145418,
        "Juros_R$": 2657973.49,
        "Amort_R$": 8989013.9,
        "PMT_Total": 11646987.39,
        "Saldo_Devedor_R$": 40720185.24
      },
      "total_interest_running": 105489963.33000003,
      "total_amortization_running": 111506637.44
    },
    {
      "date": "15/03/2037",
      "label": "Pagamento",
      "component": "",
      "component_label": "-",
      "payment": 11453037.24,
      "interest": 2218565.19,
      "amortization": 9234472.05,
      "balance": 32597601.41,
      "principal": 41832073.46,
      "pu_cheio": 473.66278111,
      "pu_vazio": 449.80724147,
      "pu_juros": 23.85553964,
      "pu_amort": 99.29539836,
      "pu_total": 123.150938,
      "parsed_date": "15/03/2037",
      "sort_key": "Fluxo",
      "raw": {
        "Evento": "Pagamento",
        "Data_Ref": "15/03/2037",
        "Data_Pgto": "15/03/2037",
        "DU_Juros": 125,
        "Qtde_IPCA_Aplicados": 6,
        "Ultimo_Mes_NIk": "2037-02",
        "Ultimo_Mes_NIk_1": "2037-01",
        "Ultimo_Fator_C_IPCA": 1.0045,
        "Fator_Juros": 1.053035028,
        "TAI_Amort": 0.220751,
        "PU_VNa_Ini": 437.85145418,
        "PU_VNa_Atualizado": 449.80724147,
        "PU_Juros": 23.85553964,
        "PU_Juros_Incorporado": 0.0,
        "PU_Amort": 99.29539836,
        "PU_Total_Pago": 123.150938,
        "PU_VNa_Fim": 350.51184311,
        "Juros_R$": 2218565.19,
        "Amort_R$": 9234472.05,
        "PMT_Total": 11453037.24,
        "Saldo_Devedor_R$": 32597601.41
      },
      "total_interest_running": 107708528.52000003,
      "total_amortization_running": 120741109.49
    },
    {
      "date": "15/09/2037",
      "label": "Pagamento",
      "component": "",
      "component_label": "-",
      "payment": 12225871.38,
      "interest": 1790602.44,
      "amortization": 10435268.94,
      "balance": 23052428.83,
      "principal": 33487697.769999996,
      "pu_cheio": 379.33656142999996,
      "pu_vazio": 360.08277179,
      "pu_juros": 19.25378964,
      "pu_amort": 112.20719293,
      "pu_total": 131.46098257,
      "parsed_date": "15/09/2037",
      "sort_key": "Fluxo",
      "raw": {
        "Evento": "Pagamento",
        "Data_Ref": "15/09/2037",
        "Data_Pgto": "15/09/2037",
        "DU_Juros": 126,
        "Qtde_IPCA_Aplicados": 6,
        "Ultimo_Mes_NIk": "2037-08",
        "Ultimo_Mes_NIk_1": "2037-07",
        "Ultimo_Fator_C_IPCA": 1.0045,
        "Fator_Juros": 1.053470455,
        "TAI_Amort": 0.311615,
        "PU_VNa_Ini": 350.51184311,
        "PU_VNa_Atualizado": 360.08277179,
        "PU_Juros": 19.25378964,
        "PU_Juros_Incorporado": 0.0,
        "PU_Amort": 112.20719293,
        "PU_Total_Pago": 131.46098257,
        "PU_VNa_Fim": 247.87557886,
        "Juros_R$": 1790602.44,
        "Amort_R$": 10435268.94,
        "PMT_Total": 12225871.38,
        "Saldo_Devedor_R$": 23052428.83
      },
      "total_interest_running": 109499130.96000002,
      "total_amortization_running": 131176378.42999999
    },
    {
      "date": "15/03/2038",
      "label": "Pagamento",
      "component": "",
      "component_label": "-",
      "payment": 11945258.97,
      "interest": 1225059.98,
      "amortization": 10720198.99,
      "balance": 12961689.76,
      "principal": 23681888.75,
      "pu_cheio": 267.81665294,
      "pu_vazio": 254.64396495,
      "pu_juros": 13.17268799,
      "pu_amort": 115.27095683,
      "pu_total": 128.44364482,
      "parsed_date": "15/03/2038",
      "sort_key": "Fluxo",
      "raw": {
        "Evento": "Pagamento",
        "Data_Ref": "15/03/2038",
        "Data_Pgto": "15/03/2038",
        "DU_Juros": 122,
        "Qtde_IPCA_Aplicados": 6,
        "Ultimo_Mes_NIk": "2038-02",
        "Ultimo_Mes_NIk_1": "2038-01",
        "Ultimo_Fator_C_IPCA": 1.0045,
        "Fator_Juros": 1.051729826,
        "TAI_Amort": 0.452675,
        "PU_VNa_Ini": 247.87557886,
        "PU_VNa_Atualizado": 254.64396495,
        "PU_Juros": 13.17268799,
        "PU_Juros_Incorporado": 0.0,
        "PU_Amort": 115.27095683,
        "PU_Total_Pago": 128.44364482,
        "PU_VNa_Fim": 139.37300812,
        "Juros_R$": 1225059.98,
        "Amort_R$": 10720198.99,
        "PMT_Total": 11945258.97,
        "Saldo_Devedor_R$": 12961689.76
      },
      "total_interest_running": 110724190.94000003,
      "total_amortization_running": 141896577.42
    },
    {
      "date": "15/09/2038",
      "label": "Pagamento",
      "component": "",
      "component_label": "-",
      "payment": 14039211.41,
      "interest": 723595.22,
      "amortization": 13315616.19,
      "balance": 0.0,
      "principal": 13315616.19,
      "pu_cheio": 150.95926244999998,
      "pu_vazio": 143.17866872,
      "pu_juros": 7.78059373,
      "pu_amort": 143.17866872,
      "pu_total": 150.95926245,
      "parsed_date": "15/09/2038",
      "sort_key": "Fluxo",
      "raw": {
        "Evento": "Pagamento",
        "Data_Ref": "15/09/2038",
        "Data_Pgto": "15/09/2038",
        "DU_Juros": 128,
        "Qtde_IPCA_Aplicados": 6,
        "Ultimo_Mes_NIk": "2038-08",
        "Ultimo_Mes_NIk_1": "2038-07",
        "Ultimo_Fator_C_IPCA": 1.0045,
        "Fator_Juros": 1.05434185,
        "TAI_Amort": 1.0,
        "PU_VNa_Ini": 139.37300812,
        "PU_VNa_Atualizado": 143.17866872,
        "PU_Juros": 7.78059373,
        "PU_Juros_Incorporado": 0.0,
        "PU_Amort": 143.17866872,
        "PU_Total_Pago": 150.95926245,
        "PU_VNa_Fim": 0.0,
        "Juros_R$": 723595.22,
        "Amort_R$": 13315616.19,
        "PMT_Total": 14039211.41,
        "Saldo_Devedor_R$": 0.0
      },
      "total_interest_running": 111447786.16000003,
      "total_amortization_running": 155212193.60999998
    }
  ],
  "table_series": [
    {
      "date": "15/03/2025",
      "label": "Incorporacao Juros 1",
      "component": "",
      "component_label": "-",
      "payment": 0.0,
      "interest": 0.0,
      "amortization": 0.0,
      "balance": 100365104.82,
      "principal": 100365104.82,
      "pu_cheio": 1079.1946754500002,
      "pu_vazio": 1031.21711954,
      "pu_juros": 47.97755591,
      "pu_amort": 0.0,
      "pu_total": 0.0,
      "parsed_date": "15/03/2025",
      "sort_key": "Fluxo",
      "raw": {
        "Evento": "Incorporacao Juros 1",
        "Data_Ref": "15/03/2025",
        "Data_Pgto": "",
        "DU_Juros": 110,
        "Qtde_IPCA_Aplicados": 6,
        "Ultimo_Mes_NIk": "2025-02",
        "Ultimo_Mes_NIk_1": "2025-01",
        "Ultimo_Fator_C_IPCA": 1.01310065,
        "Fator_Juros": 1.046525174,
        "TAI_Amort": 0.0,
        "PU_VNa_Ini": 1000.0,
        "PU_VNa_Atualizado": 1031.21711954,
        "PU_Juros": 47.97755591,
        "PU_Juros_Incorporado": 47.97755591,
        "PU_Amort": 0.0,
        "PU_Total_Pago": 0.0,
        "PU_VNa_Fim": 1079.19467545,
        "Juros_R$": 0.0,
        "Amort_R$": 0.0,
        "PMT_Total": 0.0,
        "Saldo_Devedor_R$": 100365104.82
      },
      "total_interest_running": 0.0,
      "total_amortization_running": 0.0
    },
    {
      "date": "15/09/2025",
      "label": "Incorporacao Juros 2",
      "component": "",
      "component_label": "-",
      "payment": 0.0,
      "interest": 0.0,
      "amortization": 0.0,
      "balance": 107476199.25,
      "principal": 107476199.25,
      "pu_cheio": 1155.6580565000002,
      "pu_vazio": 1097.00091827,
      "pu_juros": 58.65713823,
      "pu_amort": 0.0,
      "pu_total": 0.0,
      "parsed_date": "15/09/2025",
      "sort_key": "Fluxo",
      "raw": {
        "Evento": "Incorporacao Juros 2",
        "Data_Ref": "15/09/2025",
        "Data_Pgto": "",
        "DU_Juros": 126,
        "Qtde_IPCA_Aplicados": 6,
        "Ultimo_Mes_NIk": "2025-08",
        "Ultimo_Mes_NIk_1": "2025-07",
        "Ultimo_Fator_C_IPCA": 0.99889934,
        "Fator_Juros": 1.053470455,
        "TAI_Amort": 0.0,
        "PU_VNa_Ini": 1079.19467545,
        "PU_VNa_Atualizado": 1097.00091827,
        "PU_Juros": 58.65713823,
        "PU_Juros_Incorporado": 58.65713823,
        "PU_Amort": 0.0,
        "PU_Total_Pago": 0.0,
        "PU_VNa_Fim": 1155.6580565,
        "Juros_R$": 0.0,
        "Amort_R$": 0.0,
        "PMT_Total": 0.0,
        "Saldo_Devedor_R$": 107476199.25
      },
      "total_interest_running": 0.0,
      "total_amortization_running": 0.0
    },
    {
      "date": "15/03/2026",
      "label": "Pagamento",
      "component": "",
      "component_label": "-",
      "payment": 6370070.65,
      "interest": 5821258.07,
      "amortization": 548812.58,
      "balance": 109213702.7,
      "principal": 109762515.28,
      "pu_cheio": 1242.83627252,
      "pu_vazio": 1180.24209972,
      "pu_juros": 62.5941728,
      "pu_amort": 5.90121049,
      "pu_total": 68.49538329,
      "parsed_date": "15/03/2026",
      "sort_key": "Fluxo",
      "raw": {
        "Evento": "Pagamento",
        "Data_Ref": "15/03/2026",
        "Data_Pgto": "15/03/2026",
        "DU_Juros": 125,
        "Qtde_IPCA_Aplicados": 6,
        "Ultimo_Mes_NIk": "2026-02",
        "Ultimo_Mes_NIk_1": "2026-01",
        "Ultimo_Fator_C_IPCA": 1.00699945,
        "Fator_Juros": 1.053035028,
        "TAI_Amort": 0.005,
        "PU_VNa_Ini": 1155.6580565,
        "PU_VNa_Atualizado": 1180.24209972,
        "PU_Juros": 62.5941728,
        "PU_Juros_Incorporado": 0.0,
        "PU_Amort": 5.90121049,
        "PU_Total_Pago": 68.49538329,
        "PU_VNa_Fim": 1174.34088923,
        "Juros_R$": 5821258.07,
        "Amort_R$": 548812.58,
        "PMT_Total": 6370070.65,
        "Saldo_Devedor_R$": 109213702.7
      },
      "total_interest_running": 5821258.07,
      "total_amortization_running": 548812.58
    },
    {
      "date": "15/09/2026",
      "label": "Pagamento",
      "component": "",
      "component_label": "-",
      "payment": 9348800.88,
      "interest": 5977947.13,
      "amortization": 3370853.75,
      "balance": 108428215.97,
      "principal": 111799069.72,
      "pu_cheio": 1266.41953603,
      "pu_vazio": 1202.14053467,
      "pu_juros": 64.27900136,
      "pu_amort": 36.24573926,
      "pu_total": 100.52474062,
      "parsed_date": "15/09/2026",
      "sort_key": "Fluxo",
      "raw": {
        "Evento": "Pagamento",
        "Data_Ref": "15/09/2026",
        "Data_Pgto": "15/09/2026",
        "DU_Juros": 126,
        "Qtde_IPCA_Aplicados": 6,
        "Ultimo_Mes_NIk": "2026-08",
        "Ultimo_Mes_NIk_1": "2026-07",
        "Ultimo_Fator_C_IPCA": 0.99815,
        "Fator_Juros": 1.053470455,
        "TAI_Amort": 0.030151,
        "PU_VNa_Ini": 1174.34088923,
        "PU_VNa_Atualizado": 1202.14053467,
        "PU_Juros": 64.27900136,
        "PU_Juros_Incorporado": 0.0,
        "PU_Amort": 36.24573926,
        "PU_Total_Pago": 100.52474062,
        "PU_VNa_Fim": 1165.89479541,
        "Juros_R$": 5977947.13,
        "Amort_R$": 3370853.75,
        "PMT_Total": 9348800.88,
        "Saldo_Devedor_R$": 108428215.97
      },
      "total_interest_running": 11799205.2,
      "total_amortization_running": 3919666.33
    },
    {
      "date": "15/03/2027",
      "label": "Pagamento",
      "component": "",
      "component_label": "-",
      "payment": 8816844.29,
      "interest": 5759427.5,
      "amortization": 3057416.79,
      "balance": 108279271.21,
      "principal": 111336688.0,
      "pu_cheio": 1259.09801607,
      "pu_vazio": 1197.16868814,
      "pu_juros": 61.92932793,
      "pu_amort": 32.87544934,
      "pu_total": 94.80477727,
      "parsed_date": "15/03/2027",
      "sort_key": "Fluxo",
      "raw": {
        "Evento": "Pagamento",
        "Data_Ref": "15/03/2027",
        "Data_Pgto": "15/03/2027",
        "DU_Juros": 122,
        "Qtde_IPCA_Aplicados": 6,
        "Ultimo_Mes_NIk": "2027-02",
        "Ultimo_Mes_NIk_1": "2027-01",
        "Ultimo_Fator_C_IPCA": 1.006192,
        "Fator_Juros": 1.051729826,
        "TAI_Amort": 0.027461,
        "PU_VNa_Ini": 1165.89479541,
        "PU_VNa_Atualizado": 1197.16868814,
        "PU_Juros": 61.92932793,
        "PU_Juros_Incorporado": 0.0,
        "PU_Amort": 32.87544934,
        "PU_Total_Pago": 94.80477727,
        "PU_VNa_Fim": 1164.2932388,
        "Juros_R$": 5759427.5,
        "Amort_R$": 3057416.79,
        "PMT_Total": 8816844.29,
        "Saldo_Devedor_R$": 108279271.21
      },
      "total_interest_running": 17558632.7,
      "total_amortization_running": 6977083.12
    },
    {
      "date": "15/09/2027",
      "label": "Pagamento",
      "component": "",
      "component_label": "-",
      "payment": 9213561.04,
      "interest": 5985878.84,
      "amortization": 3227682.2,
      "balance": 106924600.86,
      "principal": 110152283.06,
      "pu_cheio": 1248.79743982,
      "pu_vazio": 1184.43315119,
      "pu_juros": 64.36428863,
      "pu_amort": 34.70626019,
      "pu_total": 99.07054882,
      "parsed_date": "15/09/2027",
      "sort_key": "Fluxo",
      "raw": {
        "Evento": "Pagamento",
        "Data_Ref": "15/09/2027",
        "Data_Pgto": "15/09/2027",
        "DU_Juros": 128,
        "Qtde_IPCA_Aplicados": 6,
        "Ultimo_Mes_NIk": "2027-08",
        "Ultimo_Mes_NIk_1": "2027-07",
        "Ultimo_Fator_C_IPCA": 1.0018,
        "Fator_Juros": 1.05434185,
        "TAI_Amort": 0.029302,
        "PU_VNa_Ini": 1164.2932388,
        "PU_VNa_Atualizado": 1184.43315119,
        "PU_Juros": 64.36428863,
        "PU_Juros_Incorporado": 0.0,
        "PU_Amort": 34.70626019,
        "PU_Total_Pago": 99.07054882,
        "PU_VNa_Fim": 1149.726891,
        "Juros_R$": 5985878.84,
        "Amort_R$": 3227682.2,
        "PMT_Total": 9213561.04,
        "Saldo_Devedor_R$": 106924600.86
      },
      "total_interest_running": 23544511.54,
      "total_amortization_running": 10204765.32
    },
    {
      "date": "15/03/2028",
      "label": "Pagamento",
      "component": "",
      "component_label": "-",
      "payment": 9104738.26,
      "interest": 5802190.36,
      "amortization": 3302547.9,
      "balance": 106100436.85,
      "principal": 109402984.75,
      "pu_cheio": 1238.7653238,
      "pu_vazio": 1176.37618015,
      "pu_juros": 62.38914365,
      "pu_amort": 35.51126775,
      "pu_total": 97.9004114,
      "parsed_date": "15/03/2028",
      "sort_key": "Fluxo",
      "raw": {
        "Evento": "Pagamento",
        "Data_Ref": "15/03/2028",
        "Data_Pgto": "15/03/2028",
        "DU_Juros": 125,
        "Qtde_IPCA_Aplicados": 6,
        "Ultimo_Mes_NIk": "2028-02",
        "Ultimo_Mes_NIk_1": "2028-01",
        "Ultimo_Fator_C_IPCA": 1.00545,
        "Fator_Juros": 1.053035028,
        "TAI_Amort": 0.030187,
        "PU_VNa_Ini": 1149.726891,
        "PU_VNa_Atualizado": 1176.37618015,
        "PU_Juros": 62.38914365,
        "PU_Juros_Incorporado": 0.0,
        "PU_Amort": 35.51126775,
        "PU_Total_Pago": 97.9004114,
        "PU_VNa_Fim": 1140.8649124,
        "Juros_R$": 5802190.36,
        "Amort_R$": 3302547.9,
        "PMT_Total": 9104738.26,
        "Saldo_Devedor_R$": 106100436.85
      },
      "total_interest_running": 29346701.9,
      "total_amortization_running": 13507313.22
    },
    {
      "date": "15/09/2028",
      "label": "Pagamento",
      "component": "",
      "component_label": "-",
      "payment": 9482184.82,
      "interest": 5817610.41,
      "amortization": 3664574.41,
      "balance": 104256688.82,
      "principal": 107921263.22999999,
      "pu_cheio": 1222.9986413899999,
      "pu_vazio": 1160.4436907,
      "pu_juros": 62.55495069,
      "pu_amort": 39.40402596,
      "pu_total": 101.95897665,
      "parsed_date": "15/09/2028",
      "sort_key": "Fluxo",
      "raw": {
        "Evento": "Pagamento",
        "Data_Ref": "15/09/2028",
        "Data_Pgto": "15/09/2028",
        "DU_Juros": 127,
        "Qtde_IPCA_Aplicados": 6,
        "Ultimo_Mes_NIk": "2028-08",
        "Ultimo_Mes_NIk_1": "2028-07",
        "Ultimo_Fator_C_IPCA": 1.00309268,
        "Fator_Juros": 1.053906063,
        "TAI_Amort": 0.033956,
        "PU_VNa_Ini": 1140.8649124,
        "PU_VNa_Atualizado": 1160.4436907,
        "PU_Juros": 62.55495069,
        "PU_Juros_Incorporado": 0.0,
        "PU_Amort": 39.40402596,
        "PU_Total_Pago": 101.95897665,
        "PU_VNa_Fim": 1121.03966474,
        "Juros_R$": 5817610.41,
        "Amort_R$": 3664574.41,
        "PMT_Total": 9482184.82,
        "Saldo_Devedor_R$": 104256688.82
      },
      "total_interest_running": 35164312.31,
      "total_amortization_running": 17171887.630000003
    },
    {
      "date": "15/03/2029",
      "label": "Pagamento",
      "component": "",
      "component_label": "-",
      "payment": 9176850.8,
      "interest": 5445456.04,
      "amortization": 3731394.76,
      "balance": 102427948.5,
      "principal": 106159343.26,
      "pu_cheio": 1200.05160536,
      "pu_vazio": 1141.49831462,
      "pu_juros": 58.55329074,
      "pu_amort": 40.12252426,
      "pu_total": 98.675815,
      "parsed_date": "15/03/2029",
      "sort_key": "Fluxo",
      "raw": {
        "Evento": "Pagamento",
        "Data_Ref": "15/03/2029",
        "Data_Pgto": "15/03/2029",
        "DU_Juros": 121,
        "Qtde_IPCA_Aplicados": 6,
        "Ultimo_Mes_NIk": "2029-02",
        "Ultimo_Mes_NIk_1": "2029-01",
        "Ultimo_Fator_C_IPCA": 1.00287089,
        "Fator_Juros": 1.051295118,
        "TAI_Amort": 0.035149,
        "PU_VNa_Ini": 1121.03966474,
        "PU_VNa_Atualizado": 1141.49831462,
        "PU_Juros": 58.55329074,
        "PU_Juros_Incorporado": 0.0,
        "PU_Amort": 40.12252426,
        "PU_Total_Pago": 98.675815,
        "PU_VNa_Fim": 1101.37579036,
        "Juros_R$": 5445456.04,
        "Amort_R$": 3731394.76,
        "PMT_Total": 9176850.8,
        "Saldo_Devedor_R$": 102427948.5
      },
      "total_interest_running": 40609768.35,
      "total_amortization_running": 20903282.39
    },
    {
      "date": "15/09/2029",
      "label": "Pagamento",
      "component": "",
      "component_label": "-",
      "payment": 10091614.99,
      "interest": 5662693.38,
      "amortization": 4428921.61,
      "balance": 99776094.89,
      "principal": 104205016.5,
      "pu_cheio": 1181.37322445,
      "pu_vazio": 1120.48404837,
      "pu_juros": 60.88917608,
      "pu_amort": 47.62281302,
      "pu_total": 108.5119891,
      "parsed_date": "15/09/2029",
      "sort_key": "Fluxo",
      "raw": {
        "Evento": "Pagamento",
        "Data_Ref": "15/09/2029",
        "Data_Pgto": "15/09/2029",
        "DU_Juros": 128,
        "Qtde_IPCA_Aplicados": 6,
        "Ultimo_Mes_NIk": "2029-08",
        "Ultimo_Mes_NIk_1": "2029-07",
        "Ultimo_Fator_C_IPCA": 1.00287089,
        "Fator_Juros": 1.05434185,
        "TAI_Amort": 0.042502,
        "PU_VNa_Ini": 1101.37579036,
        "PU_VNa_Atualizado": 1120.48404837,
        "PU_Juros": 60.88917608,
        "PU_Juros_Incorporado": 0.0,
        "PU_Amort": 47.62281302,
        "PU_Total_Pago": 108.5119891,
        "PU_VNa_Fim": 1072.86123535,
        "Juros_R$": 5662693.38,
        "Amort_R$": 4428921.61,
        "PMT_Total": 10091614.99,
        "Saldo_Devedor_R$": 99776094.89
      },
      "total_interest_running": 46272461.730000004,
      "total_amortization_running": 25332204.0
    },
    {
      "date": "15/03/2030",
      "label": "Pagamento",
      "component": "",
      "component_label": "-",
      "payment": 9326286.34,
      "interest": 5206821.48,
      "amortization": 4119464.86,
      "balance": 97387689.84,
      "principal": 101507154.7,
      "pu_cheio": 1147.4621093800001,
      "pu_vazio": 1091.47478167,
      "pu_juros": 55.98732771,
      "pu_amort": 44.29532106,
      "pu_total": 100.28264877,
      "parsed_date": "15/03/2030",
      "sort_key": "Fluxo",
      "raw": {
        "Evento": "Pagamento",
        "Data_Ref": "15/03/2030",
        "Data_Pgto": "15/03/2030",
        "DU_Juros": 121,
        "Qtde_IPCA_Aplicados": 6,
        "Ultimo_Mes_NIk": "2030-02",
        "Ultimo_Mes_NIk_1": "2030-01",
        "Ultimo_Fator_C_IPCA": 1.00287089,
        "Fator_Juros": 1.051295118,
        "TAI_Amort": 0.040583,
        "PU_VNa_Ini": 1072.86123535,
        "PU_VNa_Atualizado": 1091.47478167,
        "PU_Juros": 55.98732771,
        "PU_Juros_Incorporado": 0.0,
        "PU_Amort": 44.29532106,
        "PU_Total_Pago": 100.28264877,
        "PU_VNa_Fim": 1047.17946061,
        "Juros_R$": 5206821.48,
        "Amort_R$": 4119464.86,
        "PMT_Total": 9326286.34,
        "Saldo_Devedor_R$": 97387689.84
      },
      "total_interest_running": 51479283.21000001,
      "total_amortization_running": 29451668.86
    },
    {
      "date": "15/09/2030",
      "label": "Pagamento",
      "component": "",
      "component_label": "-",
      "payment": 9967955.35,
      "interest": 5384044.43,
      "amortization": 4583910.92,
      "balance": 94493401.22,
      "principal": 99077312.14,
      "pu_cheio": 1123.24039332,
      "pu_vazio": 1065.34744241,
      "pu_juros": 57.89295091,
      "pu_amort": 49.28936477,
      "pu_total": 107.18231568,
      "parsed_date": "15/09/2030",
      "sort_key": "Fluxo",
      "raw": {
        "Evento": "Pagamento",
        "Data_Ref": "15/09/2030",
        "Data_Pgto": "15/09/2030",
        "DU_Juros": 128,
        "Qtde_IPCA_Aplicados": 6,
        "Ultimo_Mes_NIk": "2030-08",
        "Ultimo_Mes_NIk_1": "2030-07",
        "Ultimo_Fator_C_IPCA": 1.00287089,
        "Fator_Juros": 1.05434185,
        "TAI_Amort": 0.046266,
        "PU_VNa_Ini": 1047.17946061,
        "PU_VNa_Atualizado": 1065.34744241,
        "PU_Juros": 57.89295091,
        "PU_Juros_Incorporado": 0.0,
        "PU_Amort": 49.28936477,
        "PU_Total_Pago": 107.18231568,
        "PU_VNa_Fim": 1016.05807764,
        "Juros_R$": 5384044.43,
        "Amort_R$": 4583910.92,
        "PMT_Total": 9967955.35,
        "Saldo_Devedor_R$": 94493401.22
      },
      "total_interest_running": 56863327.64000001,
      "total_amortization_running": 34035579.78
    },
    {
      "date": "15/03/2031",
      "label": "Pagamento",
      "component": "",
      "component_label": "-",
      "payment": 10419938.61,
      "interest": 5073006.29,
      "amortization": 5346932.32,
      "balance": 91098455.78,
      "principal": 96445388.1,
      "pu_cheio": 1091.5956385700001,
      "pu_vazio": 1037.04718382,
      "pu_juros": 54.54845475,
      "pu_amort": 57.49389587,
      "pu_total": 112.04235062,
      "parsed_date": "15/03/2031",
      "sort_key": "Fluxo",
      "raw": {
        "Evento": "Pagamento",
        "Data_Ref": "15/03/2031",
        "Data_Pgto": "15/03/2031",
        "DU_Juros": 124,
        "Qtde_IPCA_Aplicados": 6,
        "Ultimo_Mes_NIk": "2031-02",
        "Ultimo_Mes_NIk_1": "2031-01",
        "Ultimo_Fator_C_IPCA": 1.0045,
        "Fator_Juros": 1.052599781,
        "TAI_Amort": 0.05544,
        "PU_VNa_Ini": 1016.05807764,
        "PU_VNa_Atualizado": 1037.04718382,
        "PU_Juros": 54.54845475,
        "PU_Juros_Incorporado": 0.0,
        "PU_Amort": 57.49389587,
        "PU_Total_Pago": 112.04235062,
        "PU_VNa_Fim": 979.55328795,
        "Juros_R$": 5073006.29,
        "Amort_R$": 5346932.32,
        "PMT_Total": 10419938.61,
        "Saldo_Devedor_R$": 91098455.78
      },
      "total_interest_running": 61936333.93000001,
      "total_amortization_running": 39382512.1
    },
    {
      "date": "15/09/2031",
      "label": "Pagamento",
      "component": "",
      "component_label": "-",
      "payment": 10497017.29,
      "interest": 5004083.43,
      "amortization": 5492933.86,
      "balance": 88093017.97,
      "principal": 93585951.83,
      "pu_cheio": 1060.10790593,
      "pu_vazio": 1006.30055727,
      "pu_juros": 53.80734866,
      "pu_amort": 59.0638049,
      "pu_total": 112.87115356,
      "parsed_date": "15/09/2031",
      "sort_key": "Fluxo",
      "raw": {
        "Evento": "Pagamento",
        "Data_Ref": "15/09/2031",
        "Data_Pgto": "15/09/2031",
        "DU_Juros": 126,
        "Qtde_IPCA_Aplicados": 6,
        "Ultimo_Mes_NIk": "2031-08",
        "Ultimo_Mes_NIk_1": "2031-07",
        "Ultimo_Fator_C_IPCA": 1.0045,
        "Fator_Juros": 1.053470455,
        "TAI_Amort": 0.058694,
        "PU_VNa_Ini": 979.55328795,
        "PU_VNa_Atualizado": 1006.30055727,
        "PU_Juros": 53.80734866,
        "PU_Juros_Incorporado": 0.0,
        "PU_Amort": 59.0638049,
        "PU_Total_Pago": 112.87115356,
        "PU_VNa_Fim": 947.23675237,
        "Juros_R$": 5004083.43,
        "Amort_R$": 5492933.86,
        "PMT_Total": 10497017.29,
        "Saldo_Devedor_R$": 88093017.97
      },
      "total_interest_running": 66940417.36000001,
      "total_amortization_running": 44875445.96
    },
    {
      "date": "15/03/2032",
      "label": "Pagamento",
      "component": "",
      "component_label": "-",
      "payment": 10442528.05,
      "interest": 4799587.77,
      "amortization": 5642940.28,
      "balance": 84855508.52,
      "principal": 90498448.8,
      "pu_cheio": 1024.7100705799999,
      "pu_vazio": 973.10159998,
      "pu_juros": 51.6084706,
      "pu_amort": 60.67677716,
      "pu_total": 112.28524776,
      "parsed_date": "15/03/2032",
      "sort_key": "Fluxo",
      "raw": {
        "Evento": "Pagamento",
        "Data_Ref": "15/03/2032",
        "Data_Pgto": "15/03/2032",
        "DU_Juros": 125,
        "Qtde_IPCA_Aplicados": 6,
        "Ultimo_Mes_NIk": "2032-02",
        "Ultimo_Mes_NIk_1": "2032-01",
        "Ultimo_Fator_C_IPCA": 1.0045,
        "Fator_Juros": 1.053035028,
        "TAI_Amort": 0.062354,
        "PU_VNa_Ini": 947.23675237,
        "PU_VNa_Atualizado": 973.10159998,
        "PU_Juros": 51.6084706,
        "PU_Juros_Incorporado": 0.0,
        "PU_Amort": 60.67677716,
        "PU_Total_Pago": 112.28524776,
        "PU_VNa_Fim": 912.42482282,
        "Juros_R$": 4799587.77,
        "Amort_R$": 5642940.28,
        "PMT_Total": 10442528.05,
        "Saldo_Devedor_R$": 84855508.52
      },
      "total_interest_running": 71740005.13000001,
      "total_amortization_running": 50518386.24
    },
    {
      "date": "15/09/2032",
      "label": "Pagamento",
      "component": "",
      "component_label": "-",
      "payment": 10534090.67,
      "interest": 4737116.94,
      "amortization": 5796973.73,
      "balance": 81375563.55,
      "principal": 87172537.28,
      "pu_cheio": 988.2758519,
      "pu_vazio": 937.33911056,
      "pu_juros": 50.93674134,
      "pu_amort": 62.33305085,
      "pu_total": 113.26979219,
      "parsed_date": "15/09/2032",
      "sort_key": "Fluxo",
      "raw": {
        "Evento": "Pagamento",
        "Data_Ref": "15/09/2032",
        "Data_Pgto": "15/09/2032",
        "DU_Juros": 128,
        "Qtde_IPCA_Aplicados": 6,
        "Ultimo_Mes_NIk": "2032-08",
        "Ultimo_Mes_NIk_1": "2032-07",
        "Ultimo_Fator_C_IPCA": 1.0045,
        "Fator_Juros": 1.05434185,
        "TAI_Amort": 0.0665,
        "PU_VNa_Ini": 912.42482282,
        "PU_VNa_Atualizado": 937.33911056,
        "PU_Juros": 50.93674134,
        "PU_Juros_Incorporado": 0.0,
        "PU_Amort": 62.33305085,
        "PU_Total_Pago": 113.26979219,
        "PU_VNa_Fim": 875.00605971,
        "Juros_R$": 4737116.94,
        "Amort_R$": 5796973.73,
        "PMT_Total": 10534090.67,
        "Saldo_Devedor_R$": 81375563.55
      },
      "total_interest_running": 76477122.07000001,
      "total_amortization_running": 56315359.97
    },
    {
      "date": "15/03/2033",
      "label": "Pagamento",
      "component": "",
      "component_label": "-",
      "payment": 10352537.62,
      "interest": 4397213.9,
      "amortization": 5955323.72,
      "balance": 77642246.68,
      "principal": 83597570.4,
      "pu_cheio": 946.18047631,
      "pu_vazio": 898.89860647,
      "pu_juros": 47.28186984,
      "pu_amort": 64.03573892,
      "pu_total": 111.31760876,
      "parsed_date": "15/03/2033",
      "sort_key": "Fluxo",
      "raw": {
        "Evento": "Pagamento",
        "Data_Ref": "15/03/2033",
        "Data_Pgto": "15/03/2033",
        "DU_Juros": 124,
        "Qtde_IPCA_Aplicados": 6,
        "Ultimo_Mes_NIk": "2033-02",
        "Ultimo_Mes_NIk_1": "2033-01",
        "Ultimo_Fator_C_IPCA": 1.0045,
        "Fator_Juros": 1.052599781,
        "TAI_Amort": 0.071238,
        "PU_VNa_Ini": 875.00605971,
        "PU_VNa_Atualizado": 898.89860647,
        "PU_Juros": 47.28186984,
        "PU_Juros_Incorporado": 0.0,
        "PU_Amort": 64.03573892,
        "PU_Total_Pago": 111.31760876,
        "PU_VNa_Fim": 834.86286755,
        "Juros_R$": 4397213.9,
        "Amort_R$": 5955323.72,
        "PMT_Total": 10352537.62,
        "Saldo_Devedor_R$": 77642246.68
      },
      "total_interest_running": 80874335.97000001,
      "total_amortization_running": 62270683.69
    },
    {
      "date": "15/09/2033",
      "label": "Pagamento",
      "component": "",
      "component_label": "-",
      "payment": 9687599.54,
      "interest": 4334431.66,
      "amortization": 5353167.88,
      "balance": 74409145.27,
      "principal": 79762313.14999999,
      "pu_cheio": 904.2660732200001,
      "pu_vazio": 857.65928121,
      "pu_juros": 46.60679201,
      "pu_amort": 57.56094499,
      "pu_total": 104.167737,
      "parsed_date": "15/09/2033",
      "sort_key": "Fluxo",
      "raw": {
        "Evento": "Pagamento",
        "Data_Ref": "15/09/2033",
        "Data_Pgto": "15/09/2033",
        "DU_Juros": 128,
        "Qtde_IPCA_Aplicados": 6,
        "Ultimo_Mes_NIk": "2033-08",
        "Ultimo_Mes_NIk_1": "2033-07",
        "Ultimo_Fator_C_IPCA": 1.0045,
        "Fator_Juros": 1.05434185,
        "TAI_Amort": 0.067114,
        "PU_VNa_Ini": 834.86286755,
        "PU_VNa_Atualizado": 857.65928121,
        "PU_Juros": 46.60679201,
        "PU_Juros_Incorporado": 0.0,
        "PU_Amort": 57.56094499,
        "PU_Total_Pago": 104.167737,
        "PU_VNa_Fim": 800.09833622,
        "Juros_R$": 4334431.66,
        "Amort_R$": 5353167.88,
        "PMT_Total": 9687599.54,
        "Saldo_Devedor_R$": 74409145.27
      },
      "total_interest_running": 85208767.63000001,
      "total_amortization_running": 67623851.57
    },
    {
      "date": "15/03/2034",
      "label": "Pagamento",
      "component": "",
      "component_label": "-",
      "payment": 11091332.88,
      "interest": 4020776.18,
      "amortization": 7070556.7,
      "balance": 69370373.33,
      "principal": 76440930.03,
      "pu_cheio": 865.1796367100001,
      "pu_vazio": 821.94548425,
      "pu_juros": 43.23415246,
      "pu_amort": 76.02749145,
      "pu_total": 119.26164391,
      "parsed_date": "15/03/2034",
      "sort_key": "Fluxo",
      "raw": {
        "Evento": "Pagamento",
        "Data_Ref": "15/03/2034",
        "Data_Pgto": "15/03/2034",
        "DU_Juros": 124,
        "Qtde_IPCA_Aplicados": 6,
        "Ultimo_Mes_NIk": "2034-02",
        "Ultimo_Mes_NIk_1": "2034-01",
        "Ultimo_Fator_C_IPCA": 1.0045,
        "Fator_Juros": 1.052599781,
        "TAI_Amort": 0.092497,
        "PU_VNa_Ini": 800.09833622,
        "PU_VNa_Atualizado": 821.94548425,
        "PU_Juros": 43.23415246,
        "PU_Juros_Incorporado": 0.0,
        "PU_Amort": 76.02749145,
        "PU_Total_Pago": 119.26164391,
        "PU_VNa_Fim": 745.9179928,
        "Juros_R$": 4020776.18,
        "Amort_R$": 7070556.7,
        "PMT_Total": 11091332.88,
        "Saldo_Devedor_R$": 69370373.33
      },
      "total_interest_running": 89229543.81000002,
      "total_amortization_running": 74694408.27
    },
    {
      "date": "15/09/2034",
      "label": "Pagamento",
      "component": "",
      "component_label": "-",
      "payment": 9491091.39,
      "interest": 3841592.48,
      "amortization": 5649498.91,
      "balance": 65615072.61,
      "principal": 71264571.52,
      "pu_cheio": 807.5931612200001,
      "pu_vazio": 766.28571519,
      "pu_juros": 41.30744603,
      "pu_amort": 60.74730007,
      "pu_total": 102.0547461,
      "parsed_date": "15/09/2034",
      "sort_key": "Fluxo",
      "raw": {
        "Evento": "Pagamento",
        "Data_Ref": "15/09/2034",
        "Data_Pgto": "15/09/2034",
        "DU_Juros": 127,
        "Qtde_IPCA_Aplicados": 6,
        "Ultimo_Mes_NIk": "2034-08",
        "Ultimo_Mes_NIk_1": "2034-07",
        "Ultimo_Fator_C_IPCA": 1.0045,
        "Fator_Juros": 1.053906063,
        "TAI_Amort": 0.079275,
        "PU_VNa_Ini": 745.9179928,
        "PU_VNa_Atualizado": 766.28571519,
        "PU_Juros": 41.30744603,
        "PU_Juros_Incorporado": 0.0,
        "PU_Amort": 60.74730007,
        "PU_Total_Pago": 102.0547461,
        "PU_VNa_Fim": 705.53841512,
        "Juros_R$": 3841592.48,
        "Amort_R$": 5649498.91,
        "PMT_Total": 9491091.39,
        "Saldo_Devedor_R$": 65615072.61
      },
      "total_interest_running": 93071136.29000002,
      "total_amortization_running": 80343907.17999999
    },
    {
      "date": "15/03/2035",
      "label": "Pagamento",
      "component": "",
      "component_label": "-",
      "payment": 10090525.83,
      "interest": 3457636.18,
      "amortization": 6632889.65,
      "balance": 60773840.48,
      "principal": 67406730.13,
      "pu_cheio": 761.9824334,
      "pu_vazio": 724.80354979,
      "pu_juros": 37.17888361,
      "pu_amort": 71.3213941,
      "pu_total": 108.50027771,
      "parsed_date": "15/03/2035",
      "sort_key": "Fluxo",
      "raw": {
        "Evento": "Pagamento",
        "Data_Ref": "15/03/2035",
        "Data_Pgto": "15/03/2035",
        "DU_Juros": 121,
        "Qtde_IPCA_Aplicados": 6,
        "Ultimo_Mes_NIk": "2035-02",
        "Ultimo_Mes_NIk_1": "2035-01",
        "Ultimo_Fator_C_IPCA": 1.0045,
        "Fator_Juros": 1.051295118,
        "TAI_Amort": 0.098401,
        "PU_VNa_Ini": 705.53841512,
        "PU_VNa_Atualizado": 724.80354979,
        "PU_Juros": 37.17888361,
        "PU_Juros_Incorporado": 0.0,
        "PU_Amort": 71.3213941,
        "PU_Total_Pago": 108.50027771,
        "PU_VNa_Fim": 653.48215569,
        "Juros_R$": 3457636.18,
        "Amort_R$": 6632889.65,
        "PMT_Total": 10090525.83,
        "Saldo_Devedor_R$": 60773840.48
      },
      "total_interest_running": 96528772.47000003,
      "total_amortization_running": 86976796.83
    },
    {
      "date": "15/09/2035",
      "label": "Pagamento",
      "component": "",
      "component_label": "-",
      "payment": 11058489.84,
      "interest": 3392741.31,
      "amortization": 7665748.53,
      "balance": 54767556.83,
      "principal": 62433305.36,
      "pu_cheio": 707.8069534699999,
      "pu_vazio": 671.32586407,
      "pu_juros": 36.4810894,
      "pu_amort": 82.42740356,
      "pu_total": 118.90849296,
      "parsed_date": "15/09/2035",
      "sort_key": "Fluxo",
      "raw": {
        "Evento": "Pagamento",
        "Data_Ref": "15/09/2035",
        "Data_Pgto": "15/09/2035",
        "DU_Juros": 128,
        "Qtde_IPCA_Aplicados": 6,
        "Ultimo_Mes_NIk": "2035-08",
        "Ultimo_Mes_NIk_1": "2035-07",
        "Ultimo_Fator_C_IPCA": 1.0045,
        "Fator_Juros": 1.05434185,
        "TAI_Amort": 0.122783,
        "PU_VNa_Ini": 653.48215569,
        "PU_VNa_Atualizado": 671.32586407,
        "PU_Juros": 36.4810894,
        "PU_Juros_Incorporado": 0.0,
        "PU_Amort": 82.42740356,
        "PU_Total_Pago": 118.90849296,
        "PU_VNa_Fim": 588.89846051,
        "Juros_R$": 3392741.31,
        "Amort_R$": 7665748.53,
        "PMT_Total": 11058489.84,
        "Saldo_Devedor_R$": 54767556.83
      },
      "total_interest_running": 99921513.78000003,
      "total_amortization_running": 94642545.36
    },
    {
      "date": "15/03/2036",
      "label": "Pagamento",
      "component": "",
      "component_label": "-",
      "payment": 10785554.24,
      "interest": 2910476.06,
      "amortization": 7875078.18,
      "balance": 48387938.48,
      "principal": 56263016.66,
      "pu_cheio": 636.27411524,
      "pu_vazio": 604.97867372,
      "pu_juros": 31.29544152,
      "pu_amort": 84.67825998,
      "pu_total": 115.9737015,
      "parsed_date": "15/03/2036",
      "sort_key": "Fluxo",
      "raw": {
        "Evento": "Pagamento",
        "Data_Ref": "15/03/2036",
        "Data_Pgto": "15/03/2036",
        "DU_Juros": 122,
        "Qtde_IPCA_Aplicados": 6,
        "Ultimo_Mes_NIk": "2036-02",
        "Ultimo_Mes_NIk_1": "2036-01",
        "Ultimo_Fator_C_IPCA": 1.0045,
        "Fator_Juros": 1.051729826,
        "TAI_Amort": 0.139969,
        "PU_VNa_Ini": 588.89846051,
        "PU_VNa_Atualizado": 604.97867372,
        "PU_Juros": 31.29544152,
        "PU_Juros_Incorporado": 0.0,
        "PU_Amort": 84.67825998,
        "PU_Total_Pago": 115.9737015,
        "PU_VNa_Fim": 520.30041374,
        "Juros_R$": 2910476.06,
        "Amort_R$": 7875078.18,
        "PMT_Total": 10785554.24,
        "Saldo_Devedor_R$": 48387938.48
      },
      "total_interest_running": 102831989.84000003,
      "total_amortization_running": 102517623.53999999
    },
    {
      "date": "15/09/2036",
      "label": "Pagamento",
      "component": "",
      "component_label": "-",
      "payment": 11646987.39,
      "interest": 2657973.49,
      "amortization": 8989013.9,
      "balance": 40720185.24,
      "principal": 49709199.14,
      "pu_cheio": 563.0878777600001,
      "pu_vazio": 534.5075176,
      "pu_juros": 28.58036016,
      "pu_amort": 96.65606342,
      "pu_total": 125.23642358,
      "parsed_date": "15/09/2036",
      "sort_key": "Fluxo",
      "raw": {
        "Evento": "Pagamento",
        "Data_Ref": "15/09/2036",
        "Data_Pgto": "15/09/2036",
        "DU_Juros": 126,
        "Qtde_IPCA_Aplicados": 6,
        "Ultimo_Mes_NIk": "2036-08",
        "Ultimo_Mes_NIk_1": "2036-07",
        "Ultimo_Fator_C_IPCA": 1.0045,
        "Fator_Juros": 1.053470455,
        "TAI_Amort": 0.180832,
        "PU_VNa_Ini": 520.30041374,
        "PU_VNa_Atualizado": 534.5075176,
        "PU_Juros": 28.58036016,
        "PU_Juros_Incorporado": 0.0,
        "PU_Amort": 96.65606342,
        "PU_Total_Pago": 125.23642358,
        "PU_VNa_Fim": 437.85145418,
        "Juros_R$": 2657973.49,
        "Amort_R$": 8989013.9,
        "PMT_Total": 11646987.39,
        "Saldo_Devedor_R$": 40720185.24
      },
      "total_interest_running": 105489963.33000003,
      "total_amortization_running": 111506637.44
    },
    {
      "date": "15/03/2037",
      "label": "Pagamento",
      "component": "",
      "component_label": "-",
      "payment": 11453037.24,
      "interest": 2218565.19,
      "amortization": 9234472.05,
      "balance": 32597601.41,
      "principal": 41832073.46,
      "pu_cheio": 473.66278111,
      "pu_vazio": 449.80724147,
      "pu_juros": 23.85553964,
      "pu_amort": 99.29539836,
      "pu_total": 123.150938,
      "parsed_date": "15/03/2037",
      "sort_key": "Fluxo",
      "raw": {
        "Evento": "Pagamento",
        "Data_Ref": "15/03/2037",
        "Data_Pgto": "15/03/2037",
        "DU_Juros": 125,
        "Qtde_IPCA_Aplicados": 6,
        "Ultimo_Mes_NIk": "2037-02",
        "Ultimo_Mes_NIk_1": "2037-01",
        "Ultimo_Fator_C_IPCA": 1.0045,
        "Fator_Juros": 1.053035028,
        "TAI_Amort": 0.220751,
        "PU_VNa_Ini": 437.85145418,
        "PU_VNa_Atualizado": 449.80724147,
        "PU_Juros": 23.85553964,
        "PU_Juros_Incorporado": 0.0,
        "PU_Amort": 99.29539836,
        "PU_Total_Pago": 123.150938,
        "PU_VNa_Fim": 350.51184311,
        "Juros_R$": 2218565.19,
        "Amort_R$": 9234472.05,
        "PMT_Total": 11453037.24,
        "Saldo_Devedor_R$": 32597601.41
      },
      "total_interest_running": 107708528.52000003,
      "total_amortization_running": 120741109.49
    },
    {
      "date": "15/09/2037",
      "label": "Pagamento",
      "component": "",
      "component_label": "-",
      "payment": 12225871.38,
      "interest": 1790602.44,
      "amortization": 10435268.94,
      "balance": 23052428.83,
      "principal": 33487697.769999996,
      "pu_cheio": 379.33656142999996,
      "pu_vazio": 360.08277179,
      "pu_juros": 19.25378964,
      "pu_amort": 112.20719293,
      "pu_total": 131.46098257,
      "parsed_date": "15/09/2037",
      "sort_key": "Fluxo",
      "raw": {
        "Evento": "Pagamento",
        "Data_Ref": "15/09/2037",
        "Data_Pgto": "15/09/2037",
        "DU_Juros": 126,
        "Qtde_IPCA_Aplicados": 6,
        "Ultimo_Mes_NIk": "2037-08",
        "Ultimo_Mes_NIk_1": "2037-07",
        "Ultimo_Fator_C_IPCA": 1.0045,
        "Fator_Juros": 1.053470455,
        "TAI_Amort": 0.311615,
        "PU_VNa_Ini": 350.51184311,
        "PU_VNa_Atualizado": 360.08277179,
        "PU_Juros": 19.25378964,
        "PU_Juros_Incorporado": 0.0,
        "PU_Amort": 112.20719293,
        "PU_Total_Pago": 131.46098257,
        "PU_VNa_Fim": 247.87557886,
        "Juros_R$": 1790602.44,
        "Amort_R$": 10435268.94,
        "PMT_Total": 12225871.38,
        "Saldo_Devedor_R$": 23052428.83
      },
      "total_interest_running": 109499130.96000002,
      "total_amortization_running": 131176378.42999999
    },
    {
      "date": "15/03/2038",
      "label": "Pagamento",
      "component": "",
      "component_label": "-",
      "payment": 11945258.97,
      "interest": 1225059.98,
      "amortization": 10720198.99,
      "balance": 12961689.76,
      "principal": 23681888.75,
      "pu_cheio": 267.81665294,
      "pu_vazio": 254.64396495,
      "pu_juros": 13.17268799,
      "pu_amort": 115.27095683,
      "pu_total": 128.44364482,
      "parsed_date": "15/03/2038",
      "sort_key": "Fluxo",
      "raw": {
        "Evento": "Pagamento",
        "Data_Ref": "15/03/2038",
        "Data_Pgto": "15/03/2038",
        "DU_Juros": 122,
        "Qtde_IPCA_Aplicados": 6,
        "Ultimo_Mes_NIk": "2038-02",
        "Ultimo_Mes_NIk_1": "2038-01",
        "Ultimo_Fator_C_IPCA": 1.0045,
        "Fator_Juros": 1.051729826,
        "TAI_Amort": 0.452675,
        "PU_VNa_Ini": 247.87557886,
        "PU_VNa_Atualizado": 254.64396495,
        "PU_Juros": 13.17268799,
        "PU_Juros_Incorporado": 0.0,
        "PU_Amort": 115.27095683,
        "PU_Total_Pago": 128.44364482,
        "PU_VNa_Fim": 139.37300812,
        "Juros_R$": 1225059.98,
        "Amort_R$": 10720198.99,
        "PMT_Total": 11945258.97,
        "Saldo_Devedor_R$": 12961689.76
      },
      "total_interest_running": 110724190.94000003,
      "total_amortization_running": 141896577.42
    },
    {
      "date": "15/09/2038",
      "label": "Pagamento",
      "component": "",
      "component_label": "-",
      "payment": 14039211.41,
      "interest": 723595.22,
      "amortization": 13315616.19,
      "balance": 0.0,
      "principal": 13315616.19,
      "pu_cheio": 150.95926244999998,
      "pu_vazio": 143.17866872,
      "pu_juros": 7.78059373,
      "pu_amort": 143.17866872,
      "pu_total": 150.95926245,
      "parsed_date": "15/09/2038",
      "sort_key": "Fluxo",
      "raw": {
        "Evento": "Pagamento",
        "Data_Ref": "15/09/2038",
        "Data_Pgto": "15/09/2038",
        "DU_Juros": 128,
        "Qtde_IPCA_Aplicados": 6,
        "Ultimo_Mes_NIk": "2038-08",
        "Ultimo_Mes_NIk_1": "2038-07",
        "Ultimo_Fator_C_IPCA": 1.0045,
        "Fator_Juros": 1.05434185,
        "TAI_Amort": 1.0,
        "PU_VNa_Ini": 139.37300812,
        "PU_VNa_Atualizado": 143.17866872,
        "PU_Juros": 7.78059373,
        "PU_Juros_Incorporado": 0.0,
        "PU_Amort": 143.17866872,
        "PU_Total_Pago": 150.95926245,
        "PU_VNa_Fim": 0.0,
        "Juros_R$": 723595.22,
        "Amort_R$": 13315616.19,
        "PMT_Total": 14039211.41,
        "Saldo_Devedor_R$": 0.0
      },
      "total_interest_running": 111447786.16000003,
      "total_amortization_running": 155212193.60999998
    }
  ],
  "summary": {
    "current_balance": 109213702.7,
    "current_principal": 109762515.28,
    "current_pu_cheio": 1242.83627252,
    "current_pu_vazio": 1180.24209972,
    "current_pu_juros": 62.5941728,
    "current_pu_amort": 5.90121049,
    "current_payment": 6370070.65,
    "total_interest": 111447786.16000003,
    "total_amortization": 155212193.60999998,
    "event_count": 28,
    "next_payment_date": "15/09/2026",
    "next_payment_amount": 9348800.88,
    "next_interest_amount": 5977947.13,
    "next_amortization_amount": 3370853.75,
    "last_event_date": "15/03/2026",
    "final_balance": 0.0,
    "duration_years": 6.49760463691544,
    "wal_years": 7.584017500148939
  },
  "timeline": [
    {
      "date": "15/09/2026",
      "label": "Pagamento",
      "component": "",
      "component_label": "-",
      "payment": 9348800.88,
      "interest": 5977947.13,
      "amortization": 3370853.75,
      "balance": 108428215.97,
      "principal": 111799069.72,
      "pu_cheio": 1266.41953603,
      "pu_vazio": 1202.14053467,
      "pu_juros": 64.27900136,
      "pu_amort": 36.24573926,
      "pu_total": 100.52474062,
      "parsed_date": "15/09/2026",
      "sort_key": "Fluxo",
      "raw": {
        "Evento": "Pagamento",
        "Data_Ref": "15/09/2026",
        "Data_Pgto": "15/09/2026",
        "DU_Juros": 126,
        "Qtde_IPCA_Aplicados": 6,
        "Ultimo_Mes_NIk": "2026-08",
        "Ultimo_Mes_NIk_1": "2026-07",
        "Ultimo_Fator_C_IPCA": 0.99815,
        "Fator_Juros": 1.053470455,
        "TAI_Amort": 0.030151,
        "PU_VNa_Ini": 1174.34088923,
        "PU_VNa_Atualizado": 1202.14053467,
        "PU_Juros": 64.27900136,
        "PU_Juros_Incorporado": 0.0,
        "PU_Amort": 36.24573926,
        "PU_Total_Pago": 100.52474062,
        "PU_VNa_Fim": 1165.89479541,
        "Juros_R$": 5977947.13,
        "Amort_R$": 3370853.75,
        "PMT_Total": 9348800.88,
        "Saldo_Devedor_R$": 108428215.97
      },
      "total_interest_running": 11799205.2,
      "total_amortization_running": 3919666.33
    },
    {
      "date": "15/03/2027",
      "label": "Pagamento",
      "component": "",
      "component_label": "-",
      "payment": 8816844.29,
      "interest": 5759427.5,
      "amortization": 3057416.79,
      "balance": 108279271.21,
      "principal": 111336688.0,
      "pu_cheio": 1259.09801607,
      "pu_vazio": 1197.16868814,
      "pu_juros": 61.92932793,
      "pu_amort": 32.87544934,
      "pu_total": 94.80477727,
      "parsed_date": "15/03/2027",
      "sort_key": "Fluxo",
      "raw": {
        "Evento": "Pagamento",
        "Data_Ref": "15/03/2027",
        "Data_Pgto": "15/03/2027",
        "DU_Juros": 122,
        "Qtde_IPCA_Aplicados": 6,
        "Ultimo_Mes_NIk": "2027-02",
        "Ultimo_Mes_NIk_1": "2027-01",
        "Ultimo_Fator_C_IPCA": 1.006192,
        "Fator_Juros": 1.051729826,
        "TAI_Amort": 0.027461,
        "PU_VNa_Ini": 1165.89479541,
        "PU_VNa_Atualizado": 1197.16868814,
        "PU_Juros": 61.92932793,
        "PU_Juros_Incorporado": 0.0,
        "PU_Amort": 32.87544934,
        "PU_Total_Pago": 94.80477727,
        "PU_VNa_Fim": 1164.2932388,
        "Juros_R$": 5759427.5,
        "Amort_R$": 3057416.79,
        "PMT_Total": 8816844.29,
        "Saldo_Devedor_R$": 108279271.21
      },
      "total_interest_running": 17558632.7,
      "total_amortization_running": 6977083.12
    },
    {
      "date": "15/09/2027",
      "label": "Pagamento",
      "component": "",
      "component_label": "-",
      "payment": 9213561.04,
      "interest": 5985878.84,
      "amortization": 3227682.2,
      "balance": 106924600.86,
      "principal": 110152283.06,
      "pu_cheio": 1248.79743982,
      "pu_vazio": 1184.43315119,
      "pu_juros": 64.36428863,
      "pu_amort": 34.70626019,
      "pu_total": 99.07054882,
      "parsed_date": "15/09/2027",
      "sort_key": "Fluxo",
      "raw": {
        "Evento": "Pagamento",
        "Data_Ref": "15/09/2027",
        "Data_Pgto": "15/09/2027",
        "DU_Juros": 128,
        "Qtde_IPCA_Aplicados": 6,
        "Ultimo_Mes_NIk": "2027-08",
        "Ultimo_Mes_NIk_1": "2027-07",
        "Ultimo_Fator_C_IPCA": 1.0018,
        "Fator_Juros": 1.05434185,
        "TAI_Amort": 0.029302,
        "PU_VNa_Ini": 1164.2932388,
        "PU_VNa_Atualizado": 1184.43315119,
        "PU_Juros": 64.36428863,
        "PU_Juros_Incorporado": 0.0,
        "PU_Amort": 34.70626019,
        "PU_Total_Pago": 99.07054882,
        "PU_VNa_Fim": 1149.726891,
        "Juros_R$": 5985878.84,
        "Amort_R$": 3227682.2,
        "PMT_Total": 9213561.04,
        "Saldo_Devedor_R$": 106924600.86
      },
      "total_interest_running": 23544511.54,
      "total_amortization_running": 10204765.32
    },
    {
      "date": "15/03/2028",
      "label": "Pagamento",
      "component": "",
      "component_label": "-",
      "payment": 9104738.26,
      "interest": 5802190.36,
      "amortization": 3302547.9,
      "balance": 106100436.85,
      "principal": 109402984.75,
      "pu_cheio": 1238.7653238,
      "pu_vazio": 1176.37618015,
      "pu_juros": 62.38914365,
      "pu_amort": 35.51126775,
      "pu_total": 97.9004114,
      "parsed_date": "15/03/2028",
      "sort_key": "Fluxo",
      "raw": {
        "Evento": "Pagamento",
        "Data_Ref": "15/03/2028",
        "Data_Pgto": "15/03/2028",
        "DU_Juros": 125,
        "Qtde_IPCA_Aplicados": 6,
        "Ultimo_Mes_NIk": "2028-02",
        "Ultimo_Mes_NIk_1": "2028-01",
        "Ultimo_Fator_C_IPCA": 1.00545,
        "Fator_Juros": 1.053035028,
        "TAI_Amort": 0.030187,
        "PU_VNa_Ini": 1149.726891,
        "PU_VNa_Atualizado": 1176.37618015,
        "PU_Juros": 62.38914365,
        "PU_Juros_Incorporado": 0.0,
        "PU_Amort": 35.51126775,
        "PU_Total_Pago": 97.9004114,
        "PU_VNa_Fim": 1140.8649124,
        "Juros_R$": 5802190.36,
        "Amort_R$": 3302547.9,
        "PMT_Total": 9104738.26,
        "Saldo_Devedor_R$": 106100436.85
      },
      "total_interest_running": 29346701.9,
      "total_amortization_running": 13507313.22
    },
    {
      "date": "15/09/2028",
      "label": "Pagamento",
      "component": "",
      "component_label": "-",
      "payment": 9482184.82,
      "interest": 5817610.41,
      "amortization": 3664574.41,
      "balance": 104256688.82,
      "principal": 107921263.22999999,
      "pu_cheio": 1222.9986413899999,
      "pu_vazio": 1160.4436907,
      "pu_juros": 62.55495069,
      "pu_amort": 39.40402596,
      "pu_total": 101.95897665,
      "parsed_date": "15/09/2028",
      "sort_key": "Fluxo",
      "raw": {
        "Evento": "Pagamento",
        "Data_Ref": "15/09/2028",
        "Data_Pgto": "15/09/2028",
        "DU_Juros": 127,
        "Qtde_IPCA_Aplicados": 6,
        "Ultimo_Mes_NIk": "2028-08",
        "Ultimo_Mes_NIk_1": "2028-07",
        "Ultimo_Fator_C_IPCA": 1.00309268,
        "Fator_Juros": 1.053906063,
        "TAI_Amort": 0.033956,
        "PU_VNa_Ini": 1140.8649124,
        "PU_VNa_Atualizado": 1160.4436907,
        "PU_Juros": 62.55495069,
        "PU_Juros_Incorporado": 0.0,
        "PU_Amort": 39.40402596,
        "PU_Total_Pago": 101.95897665,
        "PU_VNa_Fim": 1121.03966474,
        "Juros_R$": 5817610.41,
        "Amort_R$": 3664574.41,
        "PMT_Total": 9482184.82,
        "Saldo_Devedor_R$": 104256688.82
      },
      "total_interest_running": 35164312.31,
      "total_amortization_running": 17171887.630000003
    },
    {
      "date": "15/03/2029",
      "label": "Pagamento",
      "component": "",
      "component_label": "-",
      "payment": 9176850.8,
      "interest": 5445456.04,
      "amortization": 3731394.76,
      "balance": 102427948.5,
      "principal": 106159343.26,
      "pu_cheio": 1200.05160536,
      "pu_vazio": 1141.49831462,
      "pu_juros": 58.55329074,
      "pu_amort": 40.12252426,
      "pu_total": 98.675815,
      "parsed_date": "15/03/2029",
      "sort_key": "Fluxo",
      "raw": {
        "Evento": "Pagamento",
        "Data_Ref": "15/03/2029",
        "Data_Pgto": "15/03/2029",
        "DU_Juros": 121,
        "Qtde_IPCA_Aplicados": 6,
        "Ultimo_Mes_NIk": "2029-02",
        "Ultimo_Mes_NIk_1": "2029-01",
        "Ultimo_Fator_C_IPCA": 1.00287089,
        "Fator_Juros": 1.051295118,
        "TAI_Amort": 0.035149,
        "PU_VNa_Ini": 1121.03966474,
        "PU_VNa_Atualizado": 1141.49831462,
        "PU_Juros": 58.55329074,
        "PU_Juros_Incorporado": 0.0,
        "PU_Amort": 40.12252426,
        "PU_Total_Pago": 98.675815,
        "PU_VNa_Fim": 1101.37579036,
        "Juros_R$": 5445456.04,
        "Amort_R$": 3731394.76,
        "PMT_Total": 9176850.8,
        "Saldo_Devedor_R$": 102427948.5
      },
      "total_interest_running": 40609768.35,
      "total_amortization_running": 20903282.39
    }
  ],
  "meta": {
    "primary_source": "Fonte IPCA: SIDRA/IBGE Tabela 1737 v/2266 | https://apisidra.ibge.gov.br/values/t/1737/n1/all/v/2266/p/202402-203810?formato=json"
  },
  "variant_options": [],
  "variants": {},
  "selected_variant": "",
  "comparison": [
    {
      "id": "axsgoias",
      "label": "AXS Goiás",
      "full_name": "AXS Goias - Emissao 1 / Serie UNICA",
      "current_balance": 253708430.26,
      "next_payment_amount": 13142465.53,
      "total_interest": 332928650.59,
      "total_amortization": 408754761.59000003,
      "event_count": 35,
      "indexer": "IPCA + 10,40%",
      "badge": "DEB"
    },
    {
      "id": "axs11",
      "label": "AXS 11",
      "full_name": "AXS 11 - Emissao 1 / Serie UNICA",
      "current_balance": 181719598.88,
      "next_payment_amount": 14628857.54,
      "total_interest": 244948914.10000005,
      "total_amortization": 322061955.51,
      "event_count": 32,
      "indexer": "IPCA + 10,74%",
      "badge": "DEB"
    },
    {
      "id": "axs03",
      "label": "AXS 03",
      "full_name": "AXS III - Emissao 78 / Serie UNICA",
      "current_balance": 155216255.06,
      "next_payment_amount": 2005403.31,
      "total_interest": 176235761.51999986,
      "total_amortization": 220679389.01000005,
      "event_count": 168,
      "indexer": "IPCA + 11%",
      "badge": "CRI"
    },
    {
      "id": "axs04",
      "label": "AXS 04",
      "full_name": "AXS 4 - Emissao 139 / Serie UNICA",
      "current_balance": 149800620.1,
      "next_payment_amount": 2180748.73,
      "total_interest": 161835035.46000004,
      "total_amortization": 212702243.51000005,
      "event_count": 168,
      "indexer": "IPCA + 11%",
      "badge": "CRI"
    },
    {
      "id": "axs08",
      "label": "AXS 08",
      "full_name": "AXS 08 - Emissao 1 / Serie UNICA",
      "current_balance": 128255198.72,
      "next_payment_amount": 7643511.47,
      "total_interest": 176143556.36999992,
      "total_amortization": 205471236.5,
      "event_count": 34,
      "indexer": "IPCA + 11%",
      "badge": "DEB"
    },
    {
      "id": "axs01",
      "label": "AXS 01",
      "full_name": "AXS 01 - Refi / 2 Series",
      "current_balance": 116095465.8,
      "next_payment_amount": 8558056.31,
      "total_interest": 155882488.40000004,
      "total_amortization": 212784924.51,
      "event_count": 32,
      "indexer": "IPCA + 9,35% / 10,97%",
      "badge": "DEB"
    },
    {
      "id": "axs09",
      "label": "AXS 09",
      "full_name": "AXS ENERGIA 09 - Emissao 1 / Serie UNICA",
      "current_balance": 109213702.7,
      "next_payment_amount": 9348800.88,
      "total_interest": 111447786.16000003,
      "total_amortization": 155212193.60999998,
      "event_count": 28,
      "indexer": "IPCA + 10,98%",
      "badge": "DEB"
    },
    {
      "id": "axs02",
      "label": "AXS 02",
      "full_name": "AXS 02 - Consolidado CRI + Debenture",
      "current_balance": 92408907.05,
      "next_payment_amount": 1292220.68,
      "total_interest": 101995590.12999995,
      "total_amortization": 135792666.59999996,
      "event_count": 168,
      "indexer": "IPCA + 11%",
      "badge": "Portfolio"
    },
    {
      "id": "axs05",
      "label": "AXS 05",
      "full_name": "AXS 05 - 2a Emissao / 2 Series",
      "current_balance": 92037849.35,
      "next_payment_amount": 8087634.390000001,
      "total_interest": 111203260.21000002,
      "total_amortization": 161973887.31999996,
      "event_count": 32,
      "indexer": "IPCA + 9,47% / 10,97%",
      "badge": "DEB"
    },
    {
      "id": "axs10",
      "label": "AXS 10",
      "full_name": "AXS ENERGIA 10 - Emissao 1 / Serie UNICA",
      "current_balance": 73323064.79,
      "next_payment_amount": 1987311.54,
      "total_interest": 49417645.60999999,
      "total_amortization": 76590551.96,
      "event_count": 144,
      "indexer": "CDI + 6,50%",
      "badge": "DEB"
    },
    {
      "id": "axs07",
      "label": "AXS 07",
      "full_name": "AXS VII - Emissao 1 / Serie UNICA",
      "current_balance": 73115537.65,
      "next_payment_amount": 1429182.09,
      "total_interest": 47306357.160000004,
      "total_amortization": 95780426.15,
      "event_count": 119,
      "indexer": "IPCA + 10,50%",
      "badge": "DEB"
    },
    {
      "id": "axs06",
      "label": "AXS 06",
      "full_name": "AXS 06 - Emissao 2 / Serie UNICA",
      "current_balance": 32290569.96,
      "next_payment_amount": 1932904.6,
      "total_interest": 50384497.21999999,
      "total_amortization": 61575762.88999999,
      "event_count": 34,
      "indexer": "IPCA + 10,38%",
      "badge": "DEB"
    }
  ],
  "generated_at": "20/07/2026 12:07:47",
  "generated_at_iso": "2026-07-20T12:07:47"
}